Workbook

Sheet Dashboard
C2: a.m. | D2: a.a. | E2: Lucro | H2: Hipóteses
B3: TIR Fluxo | C3: =((1+Fundo!X2)^30)-1 -> 0.017423268 | D3: =((1+C3)^12)-1 -> 0.23032539 | H3: Média compra | I3: 1678
B4: TIR Fundo | H4: Média venda | I4: 1750
B5: TIR Senior | C5: =((1+Fundo!AD2)^30)-1 -> 0.013841877 | D5: =((1+C5)^12)-1 -> 0.17935 | E5: =Fundo!AD5+Fundo!AD399 -> 118720.81 | H5: Taxa antecipação | I5: =I4/I3-1 -> 0.042908224
B6: TIR Meza | C6: =((1+Fundo!AJ2)^30)-1 -> 0.015467976 | D6: =((1+C6)^12)-1 -> 0.20225 | E6: =Fundo!AJ5+Fundo!AJ399 -> 22334.753 | H6: Lucro | I6: =I4-I3 -> 72
B7: TIR Jr | C7: =((1+Fundo!AN2)^30)-1 -> 0.021937258 | D7: =((1+C7)^12)-1 -> 0.29745049 | E7: =Fundo!AN5+Fundo!AN399 -> 98926.464
H8: Originações por dia | I8: 30
C9: % | D9: R$ | H9: % 18 dias | I9: 0.3
B10: Sênior | C10: 0.6 | D10: =$D$14*C10 -> 600000 | H10: % 20 dias | I10: 0.3
B11: Sub Meza | C11: 0.1 | D11: =$D$14*C11 -> 100000 | H11: % 22 dias | I11: 0.4
B12: Sub Jr | C12: 0.3 | D12: =$D$14*C12 -> 300000
H13: Custos
B14: Única | C14: 1 | D14: 1000000 | H14: Consultoria | I14: 0.01
H15: Taxa de Gestão | I15: 0.005 | J15: 15000
C16: Mês | D16: Ano | H16: Taxa de Adm | I16: 0.002 | J16: 15000
B17: CDI | C17: =((1+D17)^(1/12))-1 -> 0.011347621 | D17: 0.145 | H17: Taxa de Performance | I17: 0.2
B18: Senior CDI+ | C18: =((1+D18)^(1/12))-1 -> 0.0024662698 | D18: 0.03 | H18: Perf Over | I18: =((1+D17)*(1+D18))-1 -> 0.17935
B19: Meza CDI+ | C19: =((1+D19)^(1/12))-1 -> 0.0040741238 | D19: 0.05 | H19: Outros Custos
B20: Hurdle Sr | C20: =(1+C17)*(1+C18)-1 -> 0.013841877 | D20: =((1+C20)^12)-1 -> 0.17935
B21: Hurdle Meza | C21: =((1+C17)*(1+C19))-1 -> 0.015467976 | D21: =((1+C21)^12)-1 -> 0.20225
B23: MOIC | C23: =Fundo!U399/Dashboard!D14 -> 1.239982 | D23: =C23*D14 -> 1239982

Sheet Fundo
E2: Carteira 18 dias | I2: Carteira 20 dias | M2: Carteira 22 dias | Q2: Fundo | X2: =IRR(X5:X399,0.001) -> 0.0005759399 | Z2: Sênior | AD2: =IRR(AD5:AD399,0.001) -> 0.00045833678 | AF2: Subodinada Mezanino | AJ2: =IRR(AJ5:AJ399,0.001) -> 0.00051178314 | AL2: Subordinada Júnior | AN2: =IRR(AN5:AN399,0.001) -> 0.00072359828
B3: Hurdle | C3: m | D3: Data | E3: n | F3: Desembolso (-) | G3: Levantamento | I3: n | J3: Desembolso (-) | K3: Levantamento | M3: n | N3: Desembolso (-) | O3: Levantamento | Q3: n | R3: Desembolso (-) | S3: Levantamento | T3: P&L Ativos | U3: Caixa | V3: Rec LM | W3: PL Fundo | X3: Fluxo | Z3: Integralização Sr. | AA3: Juros Sr. | AB3: Amortização Sr. | AC3: PL Sr. | AD3: Fluxo Sr. | AF3: Integralização Meza | AG3: Juros Meza | AH3: Amortização Meza | AI3: PL Meza | AJ3: Fluxo Meza | AL3: Integralização Jr. | AM3: Amortização Jr. | AN3: Fluxo Jr.
C4: 0 | U4: =Z5+AF5+AL5 -> 1000000 | W4: =U4 -> 1000000 | Z4: =Dashboard!D10 -> 600000 | AF4: =Dashboard!D11 -> 100000 | AL4: =Dashboard!D12 -> 300000
B5: =Dashboard!D14 -> 1000000 | C5: 1 | D5: 46174 | E5: =Q5*Dashboard!$I$9 -> 9 | F5: =E5*Dashboard!$I$3 -> 15102 | G5: 0 | I5: =Q5*Dashboard!$I$10 -> 9 | J5: =I5*Dashboard!$I$3 -> 15102 | K5: 0 | M5: =Q5*Dashboard!$I$11 -> 12 | N5: =M5*Dashboard!$I$3 -> 20136 | O5: 0 | Q5: =Dashboard!I8 -> 30 | R5: =F5+J5+N5 -> 50340 | S5: =G5+K5+O5 -> 0 | T5: 0 | U5: =U4-R5+S5+V5-Custos!D5 -> 938660 | V5: 0 | W5: =U5+R5 -> 989000 | X5: =-R5+S5-Custos!D5 -> -61340 | Z5: =Z4 -> 600000 | AA5: =AC4*(((1+Dashboard!$C$20)^(1/30))-1) -> 0 | AB5: 0 | AC5: =Z5 -> 600000 | AD5: =-Z5+AB5 -> -600000 | AF5: =AF4 -> 100000 | AG5: =AI4*(((1+Dashboard!$C$21)^(1/30))-1) -> 0 | AH5: 0 | AI5: =AF5 -> 100000 | AJ5: =-AF5+AH5 -> -100000 | AL5: =AL4 -> 300000 | AM5: 0 | AN5: =-AL5+AM5 -> -300000
B6: =B5*(((1+Dashboard!$C$20)^(1/30))) -> 1000458.3 | C6: 2 | D6: =D5+1 -> 46175 | E6: =E5 -> 9 | F6: =E6*Dashboard!$I$3 -> 15102 | G6: 0 | I6: =I5 -> 9 | J6: =I6*Dashboard!$I$3 -> 15102 | K6: 0 | M6: =M5 -> 12 | N6: =M6*Dashboard!$I$3 -> 20136 | O6: 0 | Q6: =Q5 -> 30 | R6: =F6+J6+N6 -> 50340 | S6: =G6+K6+O6 -> 0 | T6: 0 | U6: =U5-R6+S6+V6-Custos!D6-AB5-AH5-AM5 -> 887169.72 | V6: =U5*(((1+Dashboard!$C$17)^(1/30))-1) -> 353.11895 | W6: =U6+R6 -> 937509.72 | X6: =-R6+S6-Custos!D6 -> -51843.4 | Z6: 0 | AA6: =AC5*(((1+Dashboard!$C$20)^(1/30))-1) -> 275.00207 | AB6: 0 | AC6: =AC5+AA6-AB5+Z6 -> 600275 | AD6: =-Z6+AB6 -> 0 | AF6: 0 | AG6: =AI5*(((1+Dashboard!$C$21)^(1/30))-1) -> 51.178314 | AH6: 0 | AI6: =AI5+AG6-AH5+AF6 -> 100051.18 | AJ6: =-AF6+AH6 -> 0 | AL6: 0 | AM6: 0 | AN6: =-AL6+AM6 -> 0
B7: =B6*(((1+Dashboard!$C$20)^(1/30))) -> 1000916.9 | C7: 3 | D7: =D6+1 -> 46176 | E7: =E6 -> 9 | F7: =E7*Dashboard!$I$3 -> 15102 | G7: 0 | I7: =I6 -> 9 | J7: =I7*Dashboard!$I$3 -> 15102 | K7: 0 | M7: =M6 -> 12 | N7: =M7*Dashboard!$I$3 -> 20136 | O7: 0 | Q7: =Q6 -> 30 | R7: =F7+J7+N7 -> 50340 | S7: =G7+K7+O7 -> 0 | T7: 0 | U7: =U6-R7+S7+V7-Custos!D7+Z6+AF6+AL6-AB6-AH6-AM6 -> 835660.07 | V7: =U6*(((1+Dashboard!$C$17)^(1/30))-1) -> 333.74858 | W7: =U7+R7 -> 886000.07 | X7: =-R7+S7-Custos!D7 -> -51843.4 | Z7: 0 | AA7: =AC6*(((1+Dashboard!$C$20)^(1/30))-1) -> 275.12811 | AB7: 0 | AC7: =AC6+AA7-AB6+Z7 -> 600550.13 | AD7: =-Z7+AB7 -> 0 | AF7: 0 | AG7: =AI6*(((1+Dashboard!$C$21)^(1/30))-1) -> 51.204506 | AH7: 0 | AI7: =AI6+AG7-AH6+AF7 -> 100102.38 | AJ7: =-AF7+AH7 -> 0 | AL7: 0 | AM7: 0 | AN7: =-AL7+AM7 -> 0
B8: =B7*(((1+Dashboard!$C$20)^(1/30))) -> 1001375.6 | C8: 4 | D8: =D7+1 -> 46177 | E8: =E7 -> 9 | F8: =E8*Dashboard!$I$3 -> 15102 | G8: 0 | I8: =I7 -> 9 | J8: =I8*Dashboard!$I$3 -> 15102 | K8: 0 | M8: =M7 -> 12 | N8: =M8*Dashboard!$I$3 -> 20136 | O8: 0 | Q8: =Q7 -> 30 | R8: =F8+J8+N8 -> 50340 | S8: =G8+K8+O8 -> 0 | T8: 0 | U8: =U7-R8+S8+V8-Custos!D8+Z7+AF7+AL7-AB7-AH7-AM7 -> 784131.04 | V8: =U7*(((1+Dashboard!$C$17)^(1/30))-1) -> 314.37092 | W8: =U8+R8 -> 834471.04 | X8: =-R8+S8-Custos!D8 -> -51843.4 | Z8: 0 | AA8: =AC7*(((1+Dashboard!$C$20)^(1/30))-1) -> 275.25421 | AB8: 0 | AC8: =AC7+AA8-AB7+Z8 -> 600825.38 | AD8: =-Z8+AB8 -> 0 | AF8: 0 | AG8: =AI7*(((1+Dashboard!$C$21)^(1/30))-1) -> 51.230712 | AH8: 0 | AI8: =AI7+AG8-AH7+AF8 -> 100153.61 | AJ8: =-AF8+AH8 -> 0 | AL8: 0 | AM8: 0 | AN8: =-AL8+AM8 -> 0
B9: =B8*(((1+Dashboard!$C$20)^(1/30))) -> 1001834.6 | C9: 5 | D9: =D8+1 -> 46178 | E9: =E8 -> 9 | F9: =E9*Dashboard!$I$3 -> 15102 | G9: 0 | I9: =I8 -> 9 | J9: =I9*Dashboard!$I$3 -> 15102 | K9: 0 | M9: =M8 -> 12 | N9: =M9*Dashboard!$I$3 -> 20136 | O9: 0 | Q9: =Q8 -> 30 | R9: =F9+J9+N9 -> 50340 | S9: =G9+K9+O9 -> 0 | T9: 0 | U9: =U8-R9+S9+V9-Custos!D9+Z8+AF8+AL8-AB8-AH8-AM8 -> 732582.62 | V9: =U8*(((1+Dashboard!$C$17)^(1/30))-1) -> 294.98597 | W9: =U9+R9 -> 782922.62 | X9: =-R9+S9-Custos!D9 -> -51843.4 | Z9: 0 | AA9: =AC8*(((1+Dashboard!$C$20)^(1/30))-1) -> 275.38037 | AB9: 0 | AC9: =AC8+AA9-AB8+Z9 -> 601100.76 | AD9: =-Z9+AB9 -> 0 | AF9: 0 | AG9: =AI8*(((1+Dashboard!$C$21)^(1/30))-1) -> 51.256931 | AH9: 0 | AI9: =AI8+AG9-AH8+AF9 -> 100204.87 | AJ9: =-AF9+AH9 -> 0 | AL9: 0 | AM9: 0 | AN9: =-AL9+AM9 -> 0
B10: =B9*(((1+Dashboard!$C$20)^(1/30))) -> 1002293.8 | C10: 6 | D10: =D9+1 -> 46179 | E10: =E9 -> 9 | F10: =E10*Dashboard!$I$3 -> 15102 | G10: 0 | I10: =I9 -> 9 | J10: =I10*Dashboard!$I$3 -> 15102 | K10: 0 | M10: =M9 -> 12 | N10: =M10*Dashboard!$I$3 -> 20136 | O10: 0 | Q10: =Q9 -> 30 | R10: =F10+J10+N10 -> 50340 | S10: =G10+K10+O10 -> 0 | T10: 0 | U10: =U9-R10+S10+V10-Custos!D10+Z9+AF9+AL9-AB9-AH9-AM9 -> 681014.82 | V10: =U9*(((1+Dashboard!$C$17)^(1/30))-1) -> 275.59373 | W10: =U10+R10 -> 731354.82 | X10: =-R10+S10-Custos!D10 -> -51843.4 | Z10: 0 | AA10: =AC9*(((1+Dashboard!$C$20)^(1/30))-1) -> 275.50659 | AB10: 0 | AC10: =AC9+AA10-AB9+Z10 -> 601376.27 | AD10: =-Z10+AB10 -> 0 | AF10: 0 | AG10: =AI9*(((1+Dashboard!$C$21)^(1/30))-1) -> 51.283163 | AH10: 0 | AI10: =AI9+AG10-AH9+AF10 -> 100256.15 | AJ10: =-AF10+AH10 -> 0 | AL10: 0 | AM10: 0 | AN10: =-AL10+AM10 -> 0
B11: =B10*(((1+Dashboard!$C$20)^(1/30))) -> 1002753.2 | C11: 7 | D11: =D10+1 -> 46180 | E11: =E10 -> 9 | F11: =E11*Dashboard!$I$3 -> 15102 | G11: 0 | I11: =I10 -> 9 | J11: =I11*Dashboard!$I$3 -> 15102 | K11: 0 | M11: =M10 -> 12 | N11: =M11*Dashboard!$I$3 -> 20136 | O11: 0 | Q11: =Q10 -> 30 | R11: =F11+J11+N11 -> 50340 | S11: =G11+K11+O11 -> 0 | T11: 0 | U11: =U10-R11+S11+V11-Custos!D11+Z10+AF10+AL10-AB10-AH10-AM10 -> 629427.61 | V11: =U10*(((1+Dashboard!$C$17)^(1/30))-1) -> 256.19419 | W11: =U11+R11 -> 679767.61 | X11: =-R11+S11-Custos!D11 -> -51843.4 | Z11: 0 | AA11: =AC10*(((1+Dashboard!$C$20)^(1/30))-1) -> 275.63286 | AB11: 0 | AC11: =AC10+AA11-AB10+Z11 -> 601651.9 | AD11: =-Z11+AB11 -> 0 | AF11: 0 | AG11: =AI10*(((1+Dashboard!$C$21)^(1/30))-1) -> 51.309409 | AH11: 0 | AI11: =AI10+AG11-AH10+AF11 -> 100307.46 | AJ11: =-AF11+AH11 -> 0 | AL11: 0 | AM11: 0 | AN11: =-AL11+AM11 -> 0
B12: =B11*(((1+Dashboard!$C$20)^(1/30))) -> 1003212.8 | C12: 8 | D12: =D11+1 -> 46181 | E12: =E11 -> 9 | F12: =E12*Dashboard!$I$3 -> 15102 | G12: 0 | I12: =I11 -> 9 | J12: =I12*Dashboard!$I$3 -> 15102 | K12: 0 | M12: =M11 -> 12 | N12: =M12*Dashboard!$I$3 -> 20136 | O12: 0 | Q12: =Q11 -> 30 | R12: =F12+J12+N12 -> 50340 | S12: =G12+K12+O12 -> 0 | T12: 0 | U12: =U11-R12+S12+V12-Custos!D12+Z11+AF11+AL11-AB11-AH11-AM11 -> 577821 | V12: =U11*(((1+Dashboard!$C$17)^(1/30))-1) -> 236.78735 | W12: =U12+R12 -> 628161 | X12: =-R12+S12-Custos!D12 -> -51843.4 | Z12: 0 | AA12: =AC11*(((1+Dashboard!$C$20)^(1/30))-1) -> 275.7592 | AB12: 0 | AC12: =AC11+AA12-AB11+Z12 -> 601927.66 | AD12: =-Z12+AB12 -> 0 | AF12: 0 | AG12: =AI11*(((1+Dashboard!$C$21)^(1/30))-1) -> 51.335669 | AH12: 0 | AI12: =AI11+AG12-AH11+AF12 -> 100358.8 | AJ12: =-AF12+AH12 -> 0 | AL12: 0 | AM12: 0 | AN12: =-AL12+AM12 -> 0
B13: =B12*(((1+Dashboard!$C$20)^(1/30))) -> 1003672.6 | C13: 9 | D13: =D12+1 -> 46182 | E13: =E12 -> 9 | F13: =E13*Dashboard!$I$3 -> 15102 | G13: 0 | I13: =I12 -> 9 | J13: =I13*Dashboard!$I$3 -> 15102 | K13: 0 | M13: =M12 -> 12 | N13: =M13*Dashboard!$I$3 -> 20136 | O13: 0 | Q13: =Q12 -> 30 | R13: =F13+J13+N13 -> 50340 | S13: =G13+K13+O13 -> 0 | T13: 0 | U13: =U12-R13+S13+V13-Custos!D13+Z12+AF12+AL12-AB12-AH12-AM12 -> 526194.97 | V13: =U12*(((1+Dashboard!$C$17)^(1/30))-1) -> 217.37322 | W13: =U13+R13 -> 576534.97 | X13: =-R13+S13-Custos!D13 -> -51843.4 | Z13: 0 | AA13: =AC12*(((1+Dashboard!$C$20)^(1/30))-1) -> 275.88559 | AB13: 0 | AC13: =AC12+AA13-AB12+Z13 -> 602203.55 | AD13: =-Z13+AB13 -> 0 | AF13: 0 | AG13: =AI12*(((1+Dashboard!$C$21)^(1/30))-1) -> 51.361941 | AH13: 0 | AI13: =AI12+AG13-AH12+AF13 -> 100410.16 | AJ13: =-AF13+AH13 -> 0 | AL13: 0 | AM13: 0 | AN13: =-AL13+AM13 -> 0
B14: =B13*(((1+Dashboard!$C$20)^(1/30))) -> 1004132.6 | C14: 10 | D14: =D13+1 -> 46183 | E14: =E13 -> 9 | F14: =E14*Dashboard!$I$3 -> 15102 | G14: 0 | I14: =I13 -> 9 | J14: =I14*Dashboard!$I$3 -> 15102 | K14: 0 | M14: =M13 -> 12 | N14: =M14*Dashboard!$I$3 -> 20136 | O14: 0 | Q14: =Q13 -> 30 | R14: =F14+J14+N14 -> 50340 | S14: =G14+K14+O14 -> 0 | T14: 0 | U14: =U13-R14+S14+V14-Custos!D14+Z13+AF13+AL13-AB13-AH13-AM13 -> 474549.52 | V14: =U13*(((1+Dashboard!$C$17)^(1/30))-1) -> 197.95178 | W14: =U14+R14 -> 524889.52 | X14: =-R14+S14-Custos!D14 -> -51843.4 | Z14: 0 | AA14: =AC13*(((1+Dashboard!$C$20)^(1/30))-1) -> 276.01204 | AB14: 0 | AC14: =AC13+AA14-AB13+Z14 -> 602479.56 | AD14: =-Z14+AB14 -> 0 | AF14: 0 | AG14: =AI13*(((1+Dashboard!$C$21)^(1/30))-1) -> 51.388227 | AH14: 0 | AI14: =AI13+AG14-AH13+AF14 -> 100461.55 | AJ14: =-AF14+AH14 -> 0 | AL14: 0 | AM14: 0 | AN14: =-AL14+AM14 -> 0
B15: =B14*(((1+Dashboard!$C$20)^(1/30))) -> 1004592.8 | C15: 11 | D15: =D14+1 -> 46184 | E15: =E14 -> 9 | F15: =E15*Dashboard!$I$3 -> 15102 | G15: 0 | I15: =I14 -> 9 | J15: =I15*Dashboard!$I$3 -> 15102 | K15: 0 | M15: =M14 -> 12 | N15: =M15*Dashboard!$I$3 -> 20136 | O15: 0 | Q15: =Q14 -> 30 | R15: =F15+J15+N15 -> 50340 | S15: =G15+K15+O15 -> 0 | T15: 0 | U15: =U14-R15+S15+V15-Custos!D15+Z14+AF14+AL14-AB14-AH14-AM14 -> 422884.65 | V15: =U14*(((1+Dashboard!$C$17)^(1/30))-1) -> 178.52303 | W15: =U15+R15 -> 473224.65 | X15: =-R15+S15-Custos!D15 -> -51843.4 | Z15: 0 | AA15: =AC14*(((1+Dashboard!$C$20)^(1/30))-1) -> 276.13854 | AB15: 0 | AC15: =AC14+AA15-AB14+Z15 -> 602755.7 | AD15: =-Z15+AB15 -> 0 | AF15: 0 | AG15: =AI14*(((1+Dashboard!$C$21)^(1/30))-1) -> 51.414527 | AH15: 0 | AI15: =AI14+AG15-AH14+AF15 -> 100512.96 | AJ15: =-AF15+AH15 -> 0 | AL15: 0 | AM15: 0 | AN15: =-AL15+AM15 -> 0
B16: =B15*(((1+Dashboard!$C$20)^(1/30))) -> 1005053.3 | C16: 12 | D16: =D15+1 -> 46185 | E16: =E15 -> 9 | F16: =E16*Dashboard!$I$3 -> 15102 | G16: 0 | I16: =I15 -> 9 | J16: =I16*Dashboard!$I$3 -> 15102 | K16: 0 | M16: =M15 -> 12 | N16: =M16*Dashboard!$I$3 -> 20136 | O16: 0 | Q16: =Q15 -> 30 | R16: =F16+J16+N16 -> 50340 | S16: =G16+K16+O16 -> 0 | T16: 0 | U16: =U15-R16+S16+V16-Custos!D16+Z15+AF15+AL15-AB15-AH15-AM15 -> 371200.33 | V16: =U15*(((1+Dashboard!$C$17)^(1/30))-1) -> 159.08698 | W16: =U16+R16 -> 421540.33 | X16: =-R16+S16-Custos!D16 -> -51843.4 | Z16: 0 | AA16: =AC15*(((1+Dashboard!$C$20)^(1/30))-1) -> 276.26511 | AB16: 0 | AC16: =AC15+AA16-AB15+Z16 -> 603031.96 | AD16: =-Z16+AB16 -> 0 | AF16: 0 | AG16: =AI15*(((1+Dashboard!$C$21)^(1/30))-1) -> 51.44084 | AH16: 0 | AI16: =AI15+AG16-AH15+AF16 -> 100564.4 | AJ16: =-AF16+AH16 -> 0 | AL16: 0 | AM16: 0 | AN16: =-AL16+AM16 -> 0
B17: =B16*(((1+Dashboard!$C$20)^(1/30))) -> 1005513.9 | C17: 13 | D17: =D16+1 -> 46186 | E17: =E16 -> 9 | F17: =E17*Dashboard!$I$3 -> 15102 | G17: 0 | I17: =I16 -> 9 | J17: =I17*Dashboard!$I$3 -> 15102 | K17: 0 | M17: =M16 -> 12 | N17: =M17*Dashboard!$I$3 -> 20136 | O17: 0 | Q17: =Q16 -> 30 | R17: =F17+J17+N17 -> 50340 | S17: =G17+K17+O17 -> 0 | T17: 0 | U17: =U16-R17+S17+V17-Custos!D17+Z16+AF16+AL16-AB16-AH16-AM16 -> 319496.58 | V17: =U16*(((1+Dashboard!$C$17)^(1/30))-1) -> 139.64361 | W17: =U17+R17 -> 369836.58 | X17: =-R17+S17-Custos!D17 -> -51843.4 | Z17: 0 | AA17: =AC16*(((1+Dashboard!$C$20)^(1/30))-1) -> 276.39173 | AB17: 0 | AC17: =AC16+AA17-AB16+Z17 -> 603308.36 | AD17: =-Z17+AB17 -> 0 | AF17: 0 | AG17: =AI16*(((1+Dashboard!$C$21)^(1/30))-1) -> 51.467167 | AH17: 0 | AI17: =AI16+AG17-AH16+AF17 -> 100615.87 | AJ17: =-AF17+AH17 -> 0 | AL17: 0 | AM17: 0 | AN17: =-AL17+AM17 -> 0
B18: =B17*(((1+Dashboard!$C$20)^(1/30))) -> 1005974.8 | C18: 14 | D18: =D17+1 -> 46187 | E18: =E17 -> 9 | F18: =E18*Dashboard!$I$3 -> 15102 | G18: 0 | I18: =I17 -> 9 | J18: =I18*Dashboard!$I$3 -> 15102 | K18: 0 | M18: =M17 -> 12 | N18: =M18*Dashboard!$I$3 -> 20136 | O18: 0 | Q18: =Q17 -> 30 | R18: =F18+J18+N18 -> 50340 | S18: =G18+K18+O18 -> 0 | T18: 0 | U18: =U17-R18+S18+V18-Custos!D18+Z17+AF17+AL17-AB17-AH17-AM17 -> 267773.37 | V18: =U17*(((1+Dashboard!$C$17)^(1/30))-1) -> 120.19293 | W18: =U18+R18 -> 318113.37 | X18: =-R18+S18-Custos!D18 -> -51843.4 | Z18: 0 | AA18: =AC17*(((1+Dashboard!$C$20)^(1/30))-1) -> 276.51841 | AB18: 0 | AC18: =AC17+AA18-AB17+Z18 -> 603584.87 | AD18: =-Z18+AB18 -> 0 | AF18: 0 | AG18: =AI17*(((1+Dashboard!$C$21)^(1/30))-1) -> 51.493507 | AH18: 0 | AI18: =AI17+AG18-AH17+AF18 -> 100667.36 | AJ18: =-AF18+AH18 -> 0 | AL18: 0 | AM18: 0 | AN18: =-AL18+AM18 -> 0
... B21: =B20*(((1+Dashboard!$C$20)^(1/30))) -> 1007358.7 | C21: 17 | D21: =D20+1 -> 46190 | E21: =E20 -> 9 | F21: =E21*Dashboard!$I$3 -> 15102 | G21: 0 | I21: =I20 -> 9 | J21: =I21*Dashboard!$I$3 -> 15102 | K21: 0 | M21: =M20 -> 12 | N21: =M21*Dashboard!$I$3 -> 20136 | O21: 0 | Q21: =Q20 -> 30 | R21: =F21+J21+N21 -> 50340 | S21: =G21+K21+O21 -> 0 | T21: 0 | U21: =U20-R21+S21+V21-Custos!D21+Z20+AF20+AL20-AB20-AH20-AM20 -> 112486.97 | V21: =U20*(((1+Dashboard!$C$17)^(1/30))-1) -> 61.796973 | W21: =U21+R21 -> 162826.97 | X21: =-R21+S21-Custos!D21 -> -51843.4 | Z21: 0 | AA21: =AC20*(((1+Dashboard!$C$20)^(1/30))-1) -> 276.8988 | AB21: 0 | AC21: =AC20+AA21-AB20+Z21 -> 604415.19 | AD21: =-Z21+AB21 -> 0 | AF21: 0 | AG21: =AI20*(((1+Dashboard!$C$21)^(1/30))-1) -> 51.572608 | AH21: 0 | AI21: =AI20+AG21-AH20+AF21 -> 100822 | AJ21: =-AF21+AH21 -> 0 | AL21: 0 | AM21: 0 | AN21: =-AL21+AM21 -> 0
B22: =B21*(((1+Dashboard!$C$20)^(1/30))) -> 1007820.4 | C22: 18 | D22: =D21+1 -> 46191 | E22: =E21 -> 9 | F22: =E22*Dashboard!$I$3 -> 15102 | G22: =E5*Dashboard!$I$4 -> 15750 | I22: =I21 -> 9 | J22: =I22*Dashboard!$I$3 -> 15102 | K22: 0 | M22: =M21 -> 12 | N22: =M22*Dashboard!$I$3 -> 20136 | O22: 0 | Q22: =Q21 -> 30 | R22: =F22+J22+N22 -> 50340 | S22: =G22+K22+O22 -> 15750 | T22: =S22-R5 -> -34590 | U22: =U21-R22+S22+V22-Custos!D22+Z21+AF21+AL21-AB21-AH21-AM21 -> 76435.89 | V22: =U21*(((1+Dashboard!$C$17)^(1/30))-1) -> 42.317007 | W22: =U22+R22 -> 126775.89 | X22: =-R22+S22-Custos!D22 -> -36093.4 | Z22: 0 | AA22: =AC21*(((1+Dashboard!$C$20)^(1/30))-1) -> 277.02571 | AB22: 0 | AC22: =AC21+AA22-AB21+Z22 -> 604692.22 | AD22: =-Z22+AB22 -> 0 | AF22: 0 | AG22: =AI21*(((1+Dashboard!$C$21)^(1/30))-1) -> 51.599002 | AH22: 0 | AI22: =AI21+AG22-AH21+AF22 -> 100873.6 | AJ22: =-AF22+AH22 -> 0 | AL22: 0 | AM22: 0 | AN22: =-AL22+AM22 -> 0
B23: =B22*(((1+Dashboard!$C$20)^(1/30))) -> 1008282.3 | C23: 19 | D23: =D22+1 -> 46192 | E23: =E22 -> 9 | F23: =E23*Dashboard!$I$3 -> 15102 | G23: =E6*Dashboard!$I$4 -> 15750 | I23: =I22 -> 9 | J23: =I23*Dashboard!$I$3 -> 15102 | K23: 0 | M23: =M22 -> 12 | N23: =M23*Dashboard!$I$3 -> 20136 | O23: 0 | Q23: =Q22 -> 30 | R23: =F23+J23+N23 -> 50340 | S23: =G23+K23+O23 -> 15750 | T23: =S23-R6 -> -34590 | U23: =U22-R23+S23+V23-Custos!D23+Z22+AF22+AL22-AB22-AH22-AM22 -> 40371.245 | V23: =U22*(((1+Dashboard!$C$17)^(1/30))-1) -> 28.754779 | W23: =U23+R23 -> 90711.245 | X23: =-R23+S23-Custos!D23 -> -36093.4 | Z23: 0 | AA23: =AC22*(((1+Dashboard!$C$20)^(1/30))-1) -> 277.15268 | AB23: 0 | AC23: =AC22+AA23-AB22+Z23 -> 604969.37 | AD23: =-Z23+AB23 -> 0 | AF23: 0 | AG23: =AI22*(((1+Dashboard!$C$21)^(1/30))-1) -> 51.625409 | AH23: 0 | AI23: =AI22+AG23-AH22+AF23 -> 100925.23 | AJ23: =-AF23+AH23 -> 0 | AL23: 0 | AM23: 0 | AN23: =-AL23+AM23 -> 0
B24: =B23*(((1+Dashboard!$C$20)^(1/30))) -> 1008744.4 | C24: 20 | D24: =D23+1 -> 46193 | E24: =E23 -> 9 | F24: =E24*Dashboard!$I$3 -> 15102 | G24: =E7*Dashboard!$I$4 -> 15750 | I24: =I23 -> 9 | J24: =I24*Dashboard!$I$3 -> 15102 | K24: =I5*Dashboard!$I$4 -> 15750 | M24: =M23 -> 12 | N24: =M24*Dashboard!$I$3 -> 20136 | O24: 0 | Q24: =Q23 -> 30 | R24: =F24+J24+N24 -> 50340 | S24: =G24+K24+O24 -> 31500 | T24: =S24-R7 -> -18840 | U24: =U23-R24+S24+V24-Custos!D24+Z23+AF23+AL23-AB23-AH23-AM23 -> 20043.032 | V24: =U23*(((1+Dashboard!$C$17)^(1/30))-1) -> 15.18745 | W24: =U24+R24 -> 70383.032 | X24: =-R24+S24-Custos!D24 -> -20343.4 | Z24: 0 | AA24: =AC23*(((1+Dashboard!$C$20)^(1/30))-1) -> 277.27971 | AB24: 0 | AC24: =AC23+AA24-AB23+Z24 -> 605246.65 | AD24: =-Z24+AB24 -> 0 | AF24: 0 | AG24: =AI23*(((1+Dashboard!$C$21)^(1/30))-1) -> 51.65183 | AH24: 0 | AI24: =AI23+AG24-AH23+AF24 -> 100976.88 | AJ24: =-AF24+AH24 -> 0 | AL24: 0 | AM24: 0 | AN24: =-AL24+AM24 -> 0
B25: =B24*(((1+Dashboard!$C$20)^(1/30))) -> 1009206.8 | C25: 21 | D25: =D24+1 -> 46194 | E25: =E24 -> 9 | F25: =E25*Dashboard!$I$3 -> 15102 | G25: =E8*Dashboard!$I$4 -> 15750 | I25: =I24 -> 9 | J25: =I25*Dashboard!$I$3 -> 15102 | K25: =I6*Dashboard!$I$4 -> 15750 | M25: =M24 -> 12 | N25: =M25*Dashboard!$I$3 -> 20136 | O25: 0 | Q25: =Q24 -> 30 | R25: =F25+J25+N25 -> 50340 | S25: =G25+K25+O25 -> 31500 | T25: =S25-R8 -> -18840 | U25: =U24-R25+S25+V25-Custos!D25+Z24+AF24+AL24-AB24-AH24-AM24 -> -292.82793 | V25: =U24*(((1+Dashboard!$C$17)^(1/30))-1) -> 7.5400831 | W25: =U25+R25 -> 50047.172 | X25: =-R25+S25-Custos!D25 -> -20343.4 | Z25: 0 | AA25: =AC24*(((1+Dashboard!$C$20)^(1/30))-1) -> 277.4068 | AB25: 0 | AC25: =AC24+AA25-AB24+Z25 -> 605524.06 | AD25: =-Z25+AB25 -> 0 | AF25: 0 | AG25: =AI24*(((1+Dashboard!$C$21)^(1/30))-1) -> 51.678265 | AH25: 0 | AI25: =AI24+AG25-AH24+AF25 -> 101028.56 | AJ25: =-AF25+AH25 -> 0 | AL25: 0 | AM25: 0 | AN25: =-AL25+AM25 -> 0
B26: =B25*(((1+Dashboard!$C$20)^(1/30))) -> 1009669.3 | C26: 22 | D26: =D25+1 -> 46195 | E26: =E25 -> 9 | F26: =E26*Dashboard!$I$3 -> 15102 | G26: =E9*Dashboard!$I$4 -> 15750 | I26: =I25 -> 9 | J26: =I26*Dashboard!$I$3 -> 15102 | K26: =I7*Dashboard!$I$4 -> 15750 | M26: =M25 -> 12 | N26: =M26*Dashboard!$I$3 -> 20136 | O26: =M5*Dashboard!$I$4 -> 21000 | Q26: =Q25 -> 30 | R26: =F26+J26+N26 -> 50340 | S26: =G26+K26+O26 -> 52500 | T26: =S26-R9 -> 2160 | U26: =U25-R26+S26+V26-Custos!D26+Z25+AF25+AL25-AB25-AH25-AM25 -> 363.66191 | V26: =U25*(((1+Dashboard!$C$17)^(1/30))-1) -> -0.11016032 | W26: =U26+R26 -> 50703.662 | X26: =-R26+S26-Custos!D26 -> 656.6 | Z26: 0 | AA26: =AC25*(((1+Dashboard!$C$20)^(1/30))-1) -> 277.53395 | AB26: 0 | AC26: =AC25+AA26-AB25+Z26 -> 605801.59 | AD26: =-Z26+AB26 -> 0 | AF26: 0 | AG26: =AI25*(((1+Dashboard!$C$21)^(1/30))-1) -> 51.704713 | AH26: 0 | AI26: =AI25+AG26-AH25+AF26 -> 101080.26 | AJ26: =-AF26+AH26 -> 0 | AL26: 0 | AM26: 0 | AN26: =-AL26+AM26 -> 0
B27: =B26*(((1+Dashboard!$C$20)^(1/30))) -> 1010132.1 | C27: 23 | D27: =D26+1 -> 46196 | E27: =E26 -> 9 | F27: =E27*Dashboard!$I$3 -> 15102 | G27: =E10*Dashboard!$I$4 -> 15750 | I27: =I26 -> 9 | J27: =I27*Dashboard!$I$3 -> 15102 | K27: =I8*Dashboard!$I$4 -> 15750 | M27: =M26 -> 12 | N27: =M27*Dashboard!$I$3 -> 20136 | O27: =M6*Dashboard!$I$4 -> 21000 | Q27: =Q26 -> 30 | R27: =F27+J27+N27 -> 50340 | S27: =G27+K27+O27 -> 52500 | T27: =S27-R10 -> 2160 | U27: =U26-R27+S27+V27-Custos!D27+Z26+AF26+AL26-AB26-AH26-AM26 -> 1020.3987 | V27: =U26*(((1+Dashboard!$C$17)^(1/30))-1) -> 0.1368077 | W27: =U27+R27 -> 51360.399 | X27: =-R27+S27-Custos!D27 -> 656.6 | Z27: 0 | AA27: =AC26*(((1+Dashboard!$C$20)^(1/30))-1) -> 277.66115 | AB27: 0 | AC27: =AC26+AA27-AB26+Z27 -> 606079.25 | AD27: =-Z27+AB27 -> 0 | AF27: 0 | AG27: =AI26*(((1+Dashboard!$C$21)^(1/30))-1) -> 51.731174 | AH27: 0 | AI27: =AI26+AG27-AH26+AF27 -> 101131.99 | AJ27: =-AF27+AH27 -> 0 | AL27: 0 | AM27: 0 | AN27: =-AL27+AM27 -> 0
B28: =B27*(((1+Dashboard!$C$20)^(1/30))) -> 1010595.1 | C28: 24 | D28: =D27+1 -> 46197 | E28: =E27 -> 9 | F28: =E28*Dashboard!$I$3 -> 15102 | G28: =E11*Dashboard!$I$4 -> 15750 | I28: =I27 -> 9 | J28: =I28*Dashboard!$I$3 -> 15102 | K28: =I9*Dashboard!$I$4 -> 15750 | M28: =M27 -> 12 | N28: =M28*Dashboard!$I$3 -> 20136 | O28: =M7*Dashboard!$I$4 -> 21000 | Q28: =Q27 -> 30 | R28: =F28+J28+N28 -> 50340 | S28: =G28+K28+O28 -> 52500 | T28: =S28-R11 -> 2160 | U28: =U27-R28+S28+V28-Custos!D28+Z27+AF27+AL27-AB27-AH27-AM27 -> 1677.3826 | V28: =U27*(((1+Dashboard!$C$17)^(1/30))-1) -> 0.38386863 | W28: =U28+R28 -> 52017.383 | X28: =-R28+S28-Custos!D28 -> 656.6 | Z28: 0 | AA28: =AC27*(((1+Dashboard!$C$20)^(1/30))-1) -> 277.78841 | AB28: 0 | AC28: =AC27+AA28-AB27+Z28 -> 606357.04 | AD28: =-Z28+AB28 -> 0 | AF28: 0 | AG28: =AI27*(((1+Dashboard!$C$21)^(1/30))-1) -> 51.75765 | AH28: 0 | AI28: =AI27+AG28-AH27+AF28 -> 101183.75 | AJ28: =-AF28+AH28 -> 0 | AL28: 0 | AM28: 0 | AN28: =-AL28+AM28 -> 0
B29: =B28*(((1+Dashboard!$C$20)^(1/30))) -> 1011058.3 | C29: 25 | D29: =D28+1 -> 46198 | E29: =E28 -> 9 | F29: =E29*Dashboard!$I$3 -> 15102 | G29: =E12*Dashboard!$I$4 -> 15750 | I29: =I28 -> 9 | J29: =I29*Dashboard!$I$3 -> 15102 | K29: =I10*Dashboard!$I$4 -> 15750 | M29: =M28 -> 12 | N29: =M29*Dashboard!$I$3 -> 20136 | O29: =M8*Dashboard!$I$4 -> 21000 | Q29: =Q28 -> 30 | R29: =F29+J29+N29 -> 50340 | S29: =G29+K29+O29 -> 52500 | T29: =S29-R12 -> 2160 | U29: =U28-R29+S29+V29-Custos!D29+Z28+AF28+AL28-AB28-AH28-AM28 -> 2334.6136 | V29: =U28*(((1+Dashboard!$C$17)^(1/30))-1) -> 0.6310225 | W29: =U29+R29 -> 52674.614 | X29: =-R29+S29-Custos!D29 -> 656.6 | Z29: 0 | AA29: =AC28*(((1+Dashboard!$C$20)^(1/30))-1) -> 277.91573 | AB29: 0 | AC29: =AC28+AA29-AB28+Z29 -> 606634.95 | AD29: =-Z29+AB29 -> 0 | AF29: 0 | AG29: =AI28*(((1+Dashboard!$C$21)^(1/30))-1) -> 51.784138 | AH29: 0 | AI29: =AI28+AG29-AH28+AF29 -> 101235.54 | AJ29: =-AF29+AH29 -> 0 | AL29: 0 | AM29: 0 | AN29: =-AL29+AM29 -> 0
B30: =B29*(((1+Dashboard!$C$20)^(1/30))) -> 1011521.7 | C30: 26 | D30: =D29+1 -> 46199 | E30: =E29 -> 9 | F30: =E30*Dashboard!$I$3 -> 15102 | G30: =E13*Dashboard!$I$4 -> 15750 | I30: =I29 -> 9 | J30: =I30*Dashboard!$I$3 -> 15102 | K30: =I11*Dashboard!$I$4 -> 15750 | M30: =M29 -> 12 | N30: =M30*Dashboard!$I$3 -> 20136 | O30: =M9*Dashboard!$I$4 -> 21000 | Q30: =Q29 -> 30 | R30: =F30+J30+N30 -> 50340 | S30: =G30+K30+O30 -> 52500 | T30: =S30-R13 -> 2160 | U30: =U29-R30+S30+V30-Custos!D30+Z29+AF29+AL29-AB29-AH29-AM29 -> 2992.0919 | V30: =U29*(((1+Dashboard!$C$17)^(1/30))-1) -> 0.87826935 | W30: =U30+R30 -> 53332.092 | X30: =-R30+S30-Custos!D30 -> 656.6 | Z30: 0 | AA30: =AC29*(((1+Dashboard!$C$20)^(1/30))-1) -> 278.04311 | AB30: 0 | AC30: =AC29+AA30-AB29+Z30 -> 606913 | AD30: =-Z30+AB30 -> 0 | AF30: 0 | AG30: =AI29*(((1+Dashboard!$C$21)^(1/30))-1) -> 51.810641 | AH30: 0 | AI30: =AI29+AG30-AH29+AF30 -> 101287.35 | AJ30: =-AF30+AH30 -> 0 | AL30: 0 | AM30: 0 | AN30: =-AL30+AM30 -> 0
B31: =B30*(((1+Dashboard!$C$20)^(1/30))) -> 1011985.3 | C31: 27 | D31: =D30+1 -> 46200 | E31: =E30 -> 9 | F31: =E31*Dashboard!$I$3 -> 15102 | G31: =E14*Dashboard!$I$4 -> 15750 | I31: =I30 -> 9 | J31: =I31*Dashboard!$I$3 -> 15102 | K31: =I12*Dashboard!$I$4 -> 15750 | M31: =M30 -> 12 | N31: =M31*Dashboard!$I$3 -> 20136 | O31: =M10*Dashboard!$I$4 -> 21000 | Q31: =Q30 -> 30 | R31: =F31+J31+N31 -> 50340 | S31: =G31+K31+O31 -> 52500 | T31: =S31-R14 -> 2160 | U31: =U30-R31+S31+V31-Custos!D31+Z30+AF30+AL30-AB30-AH30-AM30 -> 3649.8175 | V31: =U30*(((1+Dashboard!$C$17)^(1/30))-1) -> 1.1256092 | W31: =U31+R31 -> 53989.817 | X31: =-R31+S31-Custos!D31 -> 656.6 | Z31: 0 | AA31: =AC30*(((1+Dashboard!$C$20)^(1/30))-1) -> 278.17055 | AB31: 0 | AC31: =AC30+AA31-AB30+Z31 -> 607191.17 | AD31: =-Z31+AB31 -> 0 | AF31: 0 | AG31: =AI30*(((1+Dashboard!$C$21)^(1/30))-1) -> 51.837156 | AH31: 0 | AI31: =AI30+AG31-AH30+AF31 -> 101339.18 | AJ31: =-AF31+AH31 -> 0 | AL31: 0 | AM31: 0 | AN31: =-AL31+AM31 -> 0
B32: =B31*(((1+Dashboard!$C$20)^(1/30))) -> 1012449.1 | C32: 28 | D32: =D31+1 -> 46201 | E32: =E31 -> 9 | F32: =E32*Dashboard!$I$3 -> 15102 | G32: =E15*Dashboard!$I$4 -> 15750 | I32: =I31 -> 9 | J32: =I32*Dashboard!$I$3 -> 15102 | K32: =I13*Dashboard!$I$4 -> 15750 | M32: =M31 -> 12 | N32: =M32*Dashboard!$I$3 -> 20136 | O32: =M11*Dashboard!$I$4 -> 21000 | Q32: =Q31 -> 30 | R32: =F32+J32+N32 -> 50340 | S32: =G32+K32+O32 -> 52500 | T32: =S32-R15 -> 2160 | U32: =U31-R32+S32+V32-Custos!D32+Z31+AF31+AL31-AB31-AH31-AM31 -> 4307.7905 | V32: =U31*(((1+Dashboard!$C$17)^(1/30))-1) -> 1.3730421 | W32: =U32+R32 -> 54647.791 | X32: =-R32+S32-Custos!D32 -> 656.6 | Z32: 0 | AA32: =AC31*(((1+Dashboard!$C$20)^(1/30))-1) -> 278.29804 | AB32: 0 | AC32: =AC31+AA32-AB31+Z32 -> 607469.47 | AD32: =-Z32+AB32 -> 0 | AF32: 0 | AG32: =AI31*(((1+Dashboard!$C$21)^(1/30))-1) -> 51.863686 | AH32: 0 | AI32: =AI31+AG32-AH31+AF32 -> 101391.05 | AJ32: =-AF32+AH32 -> 0 | AL32: 0 | AM32: 0 | AN32: =-AL32+AM32 -> 0
B33: =B32*(((1+Dashboard!$C$20)^(1/30))) -> 1012913.2 | C33: 29 | D33: =D32+1 -> 46202 | E33: =E32 -> 9 | F33: =E33*Dashboard!$I$3 -> 15102 | G33: =E16*Dashboard!$I$4 -> 15750 | I33: =I32 -> 9 | J33: =I33*Dashboard!$I$3 -> 15102 | K33: =I14*Dashboard!$I$4 -> 15750 | M33: =M32 -> 12 | N33: =M33*Dashboard!$I$3 -> 20136 | O33: =M12*Dashboard!$I$4 -> 21000 | Q33: =Q32 -> 30 | R33: =F33+J33+N33 -> 50340 | S33: =G33+K33+O33 -> 52500 | T33: =S33-R16 -> 2160 | U33: =U32-R33+S33+V33-Custos!D33+Z32+AF32+AL32-AB32-AH32-AM32 -> 4966.0111 | V33: =U32*(((1+Dashboard!$C$17)^(1/30))-1) -> 1.6205681 | W33: =U33+R33 -> 55306.011 | X33: =-R33+S33-Custos!D33 -> 656.6 | Z33: 0 | AA33: =AC32*(((1+Dashboard!$C$20)^(1/30))-1) -> 278.4256 | AB33: 0 | AC33: =AC32+AA33-AB32+Z33 -> 607747.89 | AD33: =-Z33+AB33 -> 0 | AF33: 0 | AG33: =AI32*(((1+Dashboard!$C$21)^(1/30))-1) -> 51.890229 | AH33: 0 | AI33: =AI32+AG33-AH32+AF33 -> 101442.94 | AJ33: =-AF33+AH33 -> 0 | AL33: 0 | AM33: 0 | AN33: =-AL33+AM33 -> 0
B34: =B33*(((1+Dashboard!$C$20)^(1/30))) -> 1013377.4 | C34: 30 | D34: =D33+1 -> 46203 | E34: =E33 -> 9 | F34: =E34*Dashboard!$I$3 -> 15102 | G34: =E17*Dashboard!$I$4 -> 15750 | I34: =I33 -> 9 | J34: =I34*Dashboard!$I$3 -> 15102 | K34: =I15*Dashboard!$I$4 -> 15750 | M34: =M33 -> 12 | N34: =M34*Dashboard!$I$3 -> 20136 | O34: =M13*Dashboard!$I$4 -> 21000 | Q34: =Q33 -> 30 | R34: =F34+J34+N34 -> 50340 | S34: =G34+K34+O34 -> 52500 | T34: =S34-R17 -> 2160 | U34: =U33-R34+S34+V34-Custos!D34+Z33+AF33+AL33-AB33-AH33-AM33 -> 5624.4793 | V34: =U33*(((1+Dashboard!$C$17)^(1/30))-1) -> 1.8681872 | W34: =U34+R34 -> 55964.479 | X34: =-R34+S34-Custos!D34 -> 656.6 | Z34: 0 | AA34: =AC33*(((1+Dashboard!$C$20)^(1/30))-1) -> 278.55321 | AB34: 0 | AC34: =AC33+AA34-AB33+Z34 -> 608026.45 | AD34: =-Z34+AB34 -> 0 | AF34: 0 | AG34: =AI33*(((1+Dashboard!$C$21)^(1/30))-1) -> 51.916785 | AH34: 0 | AI34: =AI33+AG34-AH33+AF34 -> 101494.85 | AJ34: =-AF34+AH34 -> 0 | AL34: 0 | AM34: 0 | AN34: =-AL34+AM34 -> 0
B35: =B34*(((1+Dashboard!$C$20)^(1/30))) -> 1013841.9 | C35: 31 | D35: =D34+1 -> 46204 | E35: =E34 -> 9 | F35: =E35*Dashboard!$I$3 -> 15102 | G35: =E18*Dashboard!$I$4 -> 15750 | I35: =I34 -> 9 | J35: =I35*Dashboard!$I$3 -> 15102 | K35: =I16*Dashboard!$I$4 -> 15750 | M35: =M34 -> 12 | N35: =M35*Dashboard!$I$3 -> 20136 | O35: =M14*Dashboard!$I$4 -> 21000 | Q35: =Q34 -> 30 | R35: =F35+J35+N35 -> 50340 | S35: =G35+K35+O35 -> 52500 | T35: =S35-R18 -> 2160 | U35: =U34-R35+S35+V35-Custos!D35+Z34+AF34+AL34-AB34-AH34-AM34 -> 6283.1952 | V35: =U34*(((1+Dashboard!$C$17)^(1/30))-1) -> 2.1158995 | W35: =U35+R35 -> 56623.195 | X35: =-R35+S35-Custos!D35 -> 656.6 | Z35: 0 | AA35: =AC34*(((1+Dashboard!$C$20)^(1/30))-1) -> 278.68088 | AB35: 0 | AC35: =AC34+AA35-AB34+Z35 -> 608305.13 | AD35: =-Z35+AB35 -> 0 | AF35: 0 | AG35: =AI34*(((1+Dashboard!$C$21)^(1/30))-1) -> 51.943355 | AH35: 0 | AI35: =AI34+AG35-AH34+AF35 -> 101546.8 | AJ35: =-AF35+AH35 -> 0 | AL35: 0 | AM35: 0 | AN35: =-AL35+AM35 -> 0
B36: =B35*(((1+Dashboard!$C$20)^(1/30))) -> 1014306.6 | C36: 32 | D36: =D35+1 -> 46205 | E36: =E35 -> 9 | F36: =E36*Dashboard!$I$3 -> 15102 | G36: =E19*Dashboard!$I$4 -> 15750 | I36: =I35 -> 9 | J36: =I36*Dashboard!$I$3 -> 15102 | K36: =I17*Dashboard!$I$4 -> 15750 | M36: =M35 -> 12 | N36: =M36*Dashboard!$I$3 -> 20136 | O36: =M15*Dashboard!$I$4 -> 21000 | Q36: =Q35 -> 30 | R36: =F36+J36+N36 -> 50340 | S36: =G36+K36+O36 -> 52500 | T36: =S36-R19 -> 2160 | U36: =U35-R36+S36+V36-Custos!D36+Z35+AF35+AL35-AB35-AH35-AM35 -> 6942.1589 | V36: =U35*(((1+Dashboard!$C$17)^(1/30))-1) -> 2.3637049 | W36: =U36+R36 -> 57282.159 | X36: =-R36+S36-Custos!D36 -> 656.6 | Z36: 0 | AA36: =AC35*(((1+Dashboard!$C$20)^(1/30))-1) -> 278.80861 | AB36: 0 | AC36: =AC35+AA36-AB35+Z36 -> 608583.93 | AD36: =-Z36+AB36 -> 0 | AF36: 0 | AG36: =AI35*(((1+Dashboard!$C$21)^(1/30))-1) -> 51.969939 | AH36: 0 | AI36: =AI35+AG36-AH35+AF36 -> 101598.77 | AJ36: =-AF36+AH36 -> 0 | AL36: 0 | AM36: 0 | AN36: =-AL36+AM36 -> 0
B37: =B36*(((1+Dashboard!$C$20)^(1/30))) -> 1014771.5 | C37: 33 | D37: =D36+1 -> 46206 | E37: =E36 -> 9 | F37: =E37*Dashboard!$I$3 -> 15102 | G37: =E20*Dashboard!$I$4 -> 15750 | I37: =I36 -> 9 | J37: =I37*Dashboard!$I$3 -> 15102 | K37: =I18*Dashboard!$I$4 -> 15750 | M37: =M36 -> 12 | N37: =M37*Dashboard!$I$3 -> 20136 | O37: =M16*Dashboard!$I$4 -> 21000 | Q37: =Q36 -> 30 | R37: =F37+J37+N37 -> 50340 | S37: =G37+K37+O37 -> 52500 | T37: =S37-R20 -> 2160 | U37: =U36-R37+S37+V37-Custos!D37+Z36+AF36+AL36-AB36-AH36-AM36 -> 7601.3705 | V37: =U36*(((1+Dashboard!$C$17)^(1/30))-1) -> 2.6116036 | W37: =U37+R37 -> 57941.37 | X37: =-R37+S37-Custos!D37 -> 656.6 | Z37: 0 | AA37: =AC36*(((1+Dashboard!$C$20)^(1/30))-1) -> 278.9364 | AB37: 0 | AC37: =AC36+AA37-AB36+Z37 -> 608862.87 | AD37: =-Z37+AB37 -> 0 | AF37: 0 | AG37: =AI36*(((1+Dashboard!$C$21)^(1/30))-1) -> 51.996536 | AH37: 0 | AI37: =AI36+AG37-AH36+AF37 -> 101650.76 | AJ37: =-AF37+AH37 -> 0 | AL37: 0 | AM37: 0 | AN37: =-AL37+AM37 -> 0
... B106: =B105*(((1+Dashboard!$C$20)^(1/30))) -> 1047369.1 | C106: 102 | D106: =D105+1 -> 46275 | E106: =E105 -> 9 | F106: =E106*Dashboard!$I$3 -> 15102 | G106: =E89*Dashboard!$I$4 -> 15750 | I106: =I105 -> 9 | J106: =I106*Dashboard!$I$3 -> 15102 | K106: =I87*Dashboard!$I$4 -> 15750 | M106: =M105 -> 12 | N106: =M106*Dashboard!$I$3 -> 20136 | O106: =M85*Dashboard!$I$4 -> 21000 | Q106: =Q105 -> 30 | R106: =F106+J106+N106 -> 50340 | S106: =G106+K106+O106 -> 52500 | T106: =S106-R89 -> 2160 | U106: =U105-R106+S106+V106-Custos!D106+Z105+AF105+AL105-AB105-AH105-AM105 -> 53691.011 | V106: =U105*(((1+Dashboard!$C$17)^(1/30))-1) -> 19.943763 | W106: =U106+R106 -> 104031.01 | X106: =-R106+S106-Custos!D106 -> 656.6 | Z106: 0 | AA106: =AC105*(((1+Dashboard!$C$20)^(1/30))-1) -> 287.89672 | AB106: 0 | AC106: =AC105+AA106-AB105+Z106 -> 628421.47 | AD106: =-Z106+AB106 -> 0 | AF106: 0 | AG106: =AI105*(((1+Dashboard!$C$21)^(1/30))-1) -> 53.865011 | AH106: 0 | AI106: =AI105+AG106-AH105+AF106 -> 105303.54 | AJ106: =-AF106+AH106 -> 0 | AL106: 0 | AM106: 0 | AN106: =-AL106+AM106 -> 0
B107: =B106*(((1+Dashboard!$C$20)^(1/30))) -> 1047849.2 | C107: 103 | D107: =D106+1 -> 46276 | E107: =E106 -> 9 | F107: =E107*Dashboard!$I$3 -> 15102 | G107: =E90*Dashboard!$I$4 -> 15750 | I107: =I106 -> 9 | J107: =I107*Dashboard!$I$3 -> 15102 | K107: =I88*Dashboard!$I$4 -> 15750 | M107: =M106 -> 12 | N107: =M107*Dashboard!$I$3 -> 20136 | O107: =M86*Dashboard!$I$4 -> 21000 | Q107: =E107+I107+M107 -> 30 | R107: =F107+J107+N107 -> 50340 | S107: =G107+K107+O107 -> 52500 | T107: =S107-R90 -> 2160 | U107: =U106-R107+S107+V107-Custos!D107+Z106+AF106+AL106-AB106-AH106-AM106 -> 54367.809 | V107: =U106*(((1+Dashboard!$C$17)^(1/30))-1) -> 20.198276 | W107: =U107+R107 -> 104707.81 | X107: =-R107+S107-Custos!D107 -> 656.6 | Z107: 0 | AA107: =AC106*(((1+Dashboard!$C$20)^(1/30))-1) -> 288.02867 | AB107: 0 | AC107: =AC106+AA107-AB106+Z107 -> 628709.49 | AD107: =-Z107+AB107 -> 0 | AF107: 0 | AG107: =AI106*(((1+Dashboard!$C$21)^(1/30))-1) -> 53.892578 | AH107: 0 | AI107: =AI106+AG107-AH106+AF107 -> 105357.44 | AJ107: =-AF107+AH107 -> 0 | AL107: 0 | AM107: 0 | AN107: =-AL107+AM107 -> 0
B108: =B107*(((1+Dashboard!$C$20)^(1/30))) -> 1048329.4 | C108: 104 | D108: =D107+1 -> 46277 | E108: =E107 -> 9 | F108: =E108*Dashboard!$I$3 -> 15102 | G108: =E91*Dashboard!$I$4 -> 15750 | I108: =I107 -> 9 | J108: =I108*Dashboard!$I$3 -> 15102 | K108: =I89*Dashboard!$I$4 -> 15750 | M108: =M107 -> 12 | N108: =M108*Dashboard!$I$3 -> 20136 | O108: =M87*Dashboard!$I$4 -> 21000 | Q108: =E108+I108+M108 -> 30 | R108: =F108+J108+N108 -> 50340 | S108: =G108+K108+O108 -> 52500 | T108: =S108-R91 -> 2160 | U108: =U107-R108+S108+V108-Custos!D108+Z107+AF107+AL107-AB107-AH107-AM107 -> 55044.862 | V108: =U107*(((1+Dashboard!$C$17)^(1/30))-1) -> 20.452884 | W108: =U108+R108 -> 105384.86 | X108: =-R108+S108-Custos!D108 -> 656.6 | Z108: 0 | AA108: =AC107*(((1+Dashboard!$C$20)^(1/30))-1) -> 288.16068 | AB108: 0 | AC108: =AC107+AA108-AB107+Z108 -> 628997.65 | AD108: =-Z108+AB108 -> 0 | AF108: 0 | AG108: =AI107*(((1+Dashboard!$C$21)^(1/30))-1) -> 53.920159 | AH108: 0 | AI108: =AI107+AG108-AH107+AF108 -> 105411.36 | AJ108: =-AF108+AH108 -> 0 | AL108: 0 | AM108: 0 | AN108: =-AL108+AM108 -> 0
B109: =B108*(((1+Dashboard!$C$20)^(1/30))) -> 1048809.9 | C109: 105 | D109: =D108+1 -> 46278 | E109: =E108 -> 9 | F109: =E109*Dashboard!$I$3 -> 15102 | G109: =E92*Dashboard!$I$4 -> 15750 | I109: =I108 -> 9 | J109: =I109*Dashboard!$I$3 -> 15102 | K109: =I90*Dashboard!$I$4 -> 15750 | M109: =M108 -> 12 | N109: =M109*Dashboard!$I$3 -> 20136 | O109: =M88*Dashboard!$I$4 -> 21000 | Q109: =E109+I109+M109 -> 30 | R109: =F109+J109+N109 -> 50340 | S109: =G109+K109+O109 -> 52500 | T109: =S109-R92 -> 2160 | U109: =U108-R109+S109+V109-Custos!D109+Z108+AF108+AL108-AB108-AH108-AM108 -> 55722.17 | V109: =U108*(((1+Dashboard!$C$17)^(1/30))-1) -> 20.707587 | W109: =U109+R109 -> 106062.17 | X109: =-R109+S109-Custos!D109 -> 656.6 | Z109: 0 | AA109: =AC108*(((1+Dashboard!$C$20)^(1/30))-1) -> 288.29276 | AB109: 0 | AC109: =AC108+AA109-AB108+Z109 -> 629285.95 | AD109: =-Z109+AB109 -> 0 | AF109: 0 | AG109: =AI108*(((1+Dashboard!$C$21)^(1/30))-1) -> 53.947755 | AH109: 0 | AI109: =AI108+AG109-AH108+AF109 -> 105465.3 | AJ109: =-AF109+AH109 -> 0 | AL109: 0 | AM109: 0 | AN109: =-AL109+AM109 -> 0
B110: =B109*(((1+Dashboard!$C$20)^(1/30))) -> 1049290.6 | C110: 106 | D110: =D109+1 -> 46279 | E110: =E109 -> 9 | F110: =E110*Dashboard!$I$3 -> 15102 | G110: =E93*Dashboard!$I$4 -> 15750 | I110: =I109 -> 9 | J110: =I110*Dashboard!$I$3 -> 15102 | K110: =I91*Dashboard!$I$4 -> 15750 | M110: =M109 -> 12 | N110: =M110*Dashboard!$I$3 -> 20136 | O110: =M89*Dashboard!$I$4 -> 21000 | Q110: =E110+I110+M110 -> 30 | R110: =F110+J110+N110 -> 50340 | S110: =G110+K110+O110 -> 52500 | T110: =S110-R93 -> 2160 | U110: =U109-R110+S110+V110-Custos!D110+Z109+AF109+AL109-AB109-AH109-AM109 -> 56399.732 | V110: =U109*(((1+Dashboard!$C$17)^(1/30))-1) -> 20.962387 | W110: =U110+R110 -> 106739.73 | X110: =-R110+S110-Custos!D110 -> 656.6 | Z110: 0 | AA110: =AC109*(((1+Dashboard!$C$20)^(1/30))-1) -> 288.42489 | AB110: 0 | AC110: =AC109+AA110-AB109+Z110 -> 629574.37 | AD110: =-Z110+AB110 -> 0 | AF110: 0 | AG110: =AI109*(((1+Dashboard!$C$21)^(1/30))-1) -> 53.975364 | AH110: 0 | AI110: =AI109+AG110-AH109+AF110 -> 105519.28 | AJ110: =-AF110+AH110 -> 0 | AL110: 0 | AM110: 0 | AN110: =-AL110+AM110 -> 0
B111: =B110*(((1+Dashboard!$C$20)^(1/30))) -> 1049771.5 | C111: 107 | D111: =D110+1 -> 46280 | E111: =E110 -> 9 | F111: =E111*Dashboard!$I$3 -> 15102 | G111: =E94*Dashboard!$I$4 -> 15750 | I111: =I110 -> 9 | J111: =I111*Dashboard!$I$3 -> 15102 | K111: =I92*Dashboard!$I$4 -> 15750 | M111: =M110 -> 12 | N111: =M111*Dashboard!$I$3 -> 20136 | O111: =M90*Dashboard!$I$4 -> 21000 | Q111: =E111+I111+M111 -> 30 | R111: =F111+J111+N111 -> 50340 | S111: =G111+K111+O111 -> 52500 | T111: =S111-R94 -> 2160 | U111: =U110-R111+S111+V111-Custos!D111+Z110+AF110+AL110-AB110-AH110-AM110 -> 57077.549 | V111: =U110*(((1+Dashboard!$C$17)^(1/30))-1) -> 21.217282 | W111: =U111+R111 -> 107417.55 | X111: =-R111+S111-Custos!D111 -> 656.6 | Z111: 0 | AA111: =AC110*(((1+Dashboard!$C$20)^(1/30))-1) -> 288.55709 | AB111: 0 | AC111: =AC110+AA111-AB110+Z111 -> 629862.93 | AD111: =-Z111+AB111 -> 0 | AF111: 0 | AG111: =AI110*(((1+Dashboard!$C$21)^(1/30))-1) -> 54.002988 | AH111: 0 | AI111: =AI110+AG111-AH110+AF111 -> 105573.28 | AJ111: =-AF111+AH111 -> 0 | AL111: 0 | AM111: 0 | AN111: =-AL111+AM111 -> 0
B112: =B111*(((1+Dashboard!$C$20)^(1/30))) -> 1050252.7 | C112: 108 | D112: =D111+1 -> 46281 | E112: =E111 -> 9 | F112: =E112*Dashboard!$I$3 -> 15102 | G112: =E95*Dashboard!$I$4 -> 15750 | I112: =I111 -> 9 | J112: =I112*Dashboard!$I$3 -> 15102 | K112: =I93*Dashboard!$I$4 -> 15750 | M112: =M111 -> 12 | N112: =M112*Dashboard!$I$3 -> 20136 | O112: =M91*Dashboard!$I$4 -> 21000 | Q112: =E112+I112+M112 -> 30 | R112: =F112+J112+N112 -> 50340 | S112: =G112+K112+O112 -> 52500 | T112: =S112-R95 -> 2160 | U112: =U111-R112+S112+V112-Custos!D112+Z111+AF111+AL111-AB111-AH111-AM111 -> 57755.622 | V112: =U111*(((1+Dashboard!$C$17)^(1/30))-1) -> 21.472274 | W112: =U112+R112 -> 108095.62 | X112: =-R112+S112-Custos!D112 -> 656.6 | Z112: 0 | AA112: =AC111*(((1+Dashboard!$C$20)^(1/30))-1) -> 288.68935 | AB112: 0 | AC112: =AC111+AA112-AB111+Z112 -> 630151.62 | AD112: =-Z112+AB112 -> 0 | AF112: 0 | AG112: =AI111*(((1+Dashboard!$C$21)^(1/30))-1) -> 54.030626 | AH112: 0 | AI112: =AI111+AG112-AH111+AF112 -> 105627.31 | AJ112: =-AF112+AH112 -> 0 | AL112: 0 | AM112: 0 | AN112: =-AL112+AM112 -> 0
B113: =B112*(((1+Dashboard!$C$20)^(1/30))) -> 1050734.1 | C113: 109 | D113: =D112+1 -> 46282 | E113: =E112 -> 9 | F113: =E113*Dashboard!$I$3 -> 15102 | G113: =E96*Dashboard!$I$4 -> 15750 | I113: =I112 -> 9 | J113: =I113*Dashboard!$I$3 -> 15102 | K113: =I94*Dashboard!$I$4 -> 15750 | M113: =M112 -> 12 | N113: =M113*Dashboard!$I$3 -> 20136 | O113: =M92*Dashboard!$I$4 -> 21000 | Q113: =E113+I113+M113 -> 30 | R113: =F113+J113+N113 -> 50340 | S113: =G113+K113+O113 -> 52500 | T113: =S113-R96 -> 2160 | U113: =U112-R113+S113+V113-Custos!D113+Z112+AF112+AL112-AB112-AH112-AM112 -> 58433.949 | V113: =U112*(((1+Dashboard!$C$17)^(1/30))-1) -> 21.727361 | W113: =U113+R113 -> 108773.95 | X113: =-R113+S113-Custos!D113 -> 656.6 | Z113: 0 | AA113: =AC112*(((1+Dashboard!$C$20)^(1/30))-1) -> 288.82166 | AB113: 0 | AC113: =AC112+AA113-AB112+Z113 -> 630440.44 | AD113: =-Z113+AB113 -> 0 | AF113: 0 | AG113: =AI112*(((1+Dashboard!$C$21)^(1/30))-1) -> 54.058278 | AH113: 0 | AI113: =AI112+AG113-AH112+AF113 -> 105681.37 | AJ113: =-AF113+AH113 -> 0 | AL113: 0 | AM113: 0 | AN113: =-AL113+AM113 -> 0
B114: =B113*(((1+Dashboard!$C$20)^(1/30))) -> 1051215.7 | C114: 110 | D114: =D113+1 -> 46283 | E114: =E113 -> 9 | F114: =E114*Dashboard!$I$3 -> 15102 | G114: =E97*Dashboard!$I$4 -> 15750 | I114: =I113 -> 9 | J114: =I114*Dashboard!$I$3 -> 15102 | K114: =I95*Dashboard!$I$4 -> 15750 | M114: =M113 -> 12 | N114: =M114*Dashboard!$I$3 -> 20136 | O114: =M93*Dashboard!$I$4 -> 21000 | Q114: =E114+I114+M114 -> 30 | R114: =F114+J114+N114 -> 50340 | S114: =G114+K114+O114 -> 52500 | T114: =S114-R97 -> 2160 | U114: =U113-R114+S114+V114-Custos!D114+Z113+AF113+AL113-AB113-AH113-AM113 -> 59112.531 | V114: =U113*(((1+Dashboard!$C$17)^(1/30))-1) -> 21.982544 | W114: =U114+R114 -> 109452.53 | X114: =-R114+S114-Custos!D114 -> 656.6 | Z114: 0 | AA114: =AC113*(((1+Dashboard!$C$20)^(1/30))-1) -> 288.95404 | AB114: 0 | AC114: =AC113+AA114-AB113+Z114 -> 630729.39 | AD114: =-Z114+AB114 -> 0 | AF114: 0 | AG114: =AI113*(((1+Dashboard!$C$21)^(1/30))-1) -> 54.085944 | AH114: 0 | AI114: =AI113+AG114-AH113+AF114 -> 105735.46 | AJ114: =-AF114+AH114 -> 0 | AL114: 0 | AM114: 0 | AN114: =-AL114+AM114 -> 0
B115: =B114*(((1+Dashboard!$C$20)^(1/30))) -> 1051697.5 | C115: 111 | D115: =D114+1 -> 46284 | E115: =E114 -> 9 | F115: =E115*Dashboard!$I$3 -> 15102 | G115: =E98*Dashboard!$I$4 -> 15750 | I115: =I114 -> 9 | J115: =I115*Dashboard!$I$3 -> 15102 | K115: =I96*Dashboard!$I$4 -> 15750 | M115: =M114 -> 12 | N115: =M115*Dashboard!$I$3 -> 20136 | O115: =M94*Dashboard!$I$4 -> 21000 | Q115: =E115+I115+M115 -> 30 | R115: =F115+J115+N115 -> 50340 | S115: =G115+K115+O115 -> 52500 | T115: =S115-R98 -> 2160 | U115: =U114-R115+S115+V115-Custos!D115+Z114+AF114+AL114-AB114-AH114-AM114 -> 59791.369 | V115: =U114*(((1+Dashboard!$C$17)^(1/30))-1) -> 22.237823 | W115: =U115+R115 -> 110131.37 | X115: =-R115+S115-Custos!D115 -> 656.6 | Z115: 0 | AA115: =AC114*(((1+Dashboard!$C$20)^(1/30))-1) -> 289.08648 | AB115: 0 | AC115: =AC114+AA115-AB114+Z115 -> 631018.48 | AD115: =-Z115+AB115 -> 0 | AF115: 0 | AG115: =AI114*(((1+Dashboard!$C$21)^(1/30))-1) -> 54.113624 | AH115: 0 | AI115: =AI114+AG115-AH114+AF115 -> 105789.57 | AJ115: =-AF115+AH115 -> 0 | AL115: 0 | AM115: 0 | AN115: =-AL115+AM115 -> 0
B116: =B115*(((1+Dashboard!$C$20)^(1/30))) -> 1052179.5 | C116: 112 | D116: =D115+1 -> 46285 | E116: =E115 -> 9 | F116: =E116*Dashboard!$I$3 -> 15102 | G116: =E99*Dashboard!$I$4 -> 15750 | I116: =I115 -> 9 | J116: =I116*Dashboard!$I$3 -> 15102 | K116: =I97*Dashboard!$I$4 -> 15750 | M116: =M115 -> 12 | N116: =M116*Dashboard!$I$3 -> 20136 | O116: =M95*Dashboard!$I$4 -> 21000 | Q116: =E116+I116+M116 -> 30 | R116: =F116+J116+N116 -> 50340 | S116: =G116+K116+O116 -> 52500 | T116: =S116-R99 -> 2160 | U116: =U115-R116+S116+V116-Custos!D116+Z115+AF115+AL115-AB115-AH115-AM115 -> 60470.462 | V116: =U115*(((1+Dashboard!$C$17)^(1/30))-1) -> 22.493198 | W116: =U116+R116 -> 110810.46 | X116: =-R116+S116-Custos!D116 -> 656.6 | Z116: 0 | AA116: =AC115*(((1+Dashboard!$C$20)^(1/30))-1) -> 289.21898 | AB116: 0 | AC116: =AC115+AA116-AB115+Z116 -> 631307.7 | AD116: =-Z116+AB116 -> 0 | AF116: 0 | AG116: =AI115*(((1+Dashboard!$C$21)^(1/30))-1) -> 54.141318 | AH116: 0 | AI116: =AI115+AG116-AH115+AF116 -> 105843.71 | AJ116: =-AF116+AH116 -> 0 | AL116: 0 | AM116: 0 | AN116: =-AL116+AM116 -> 0
B117: =B116*(((1+Dashboard!$C$20)^(1/30))) -> 1052661.8 | C117: 113 | D117: =D116+1 -> 46286 | E117: =E116 -> 9 | F117: =E117*Dashboard!$I$3 -> 15102 | G117: =E100*Dashboard!$I$4 -> 15750 | I117: =I116 -> 9 | J117: =I117*Dashboard!$I$3 -> 15102 | K117: =I98*Dashboard!$I$4 -> 15750 | M117: =M116 -> 12 | N117: =M117*Dashboard!$I$3 -> 20136 | O117: =M96*Dashboard!$I$4 -> 21000 | Q117: =E117+I117+M117 -> 30 | R117: =F117+J117+N117 -> 50340 | S117: =G117+K117+O117 -> 52500 | T117: =S117-R100 -> 2160 | U117: =U116-R117+S117+V117-Custos!D117+Z116+AF116+AL116-AB116-AH116-AM116 -> 61149.811 | V117: =U116*(((1+Dashboard!$C$17)^(1/30))-1) -> 22.74867 | W117: =U117+R117 -> 111489.81 | X117: =-R117+S117-Custos!D117 -> 656.6 | Z117: 0 | AA117: =AC116*(((1+Dashboard!$C$20)^(1/30))-1) -> 289.35154 | AB117: 0 | AC117: =AC116+AA117-AB116+Z117 -> 631597.05 | AD117: =-Z117+AB117 -> 0 | AF117: 0 | AG117: =AI116*(((1+Dashboard!$C$21)^(1/30))-1) -> 54.169027 | AH117: 0 | AI117: =AI116+AG117-AH116+AF117 -> 105897.88 | AJ117: =-AF117+AH117 -> 0 | AL117: 0 | AM117: 0 | AN117: =-AL117+AM117 -> 0
B118: =B117*(((1+Dashboard!$C$20)^(1/30))) -> 1053144.2 | C118: 114 | D118: =D117+1 -> 46287 | E118: =E117 -> 9 | F118: =E118*Dashboard!$I$3 -> 15102 | G118: =E101*Dashboard!$I$4 -> 15750 | I118: =I117 -> 9 | J118: =I118*Dashboard!$I$3 -> 15102 | K118: =I99*Dashboard!$I$4 -> 15750 | M118: =M117 -> 12 | N118: =M118*Dashboard!$I$3 -> 20136 | O118: =M97*Dashboard!$I$4 -> 21000 | Q118: =E118+I118+M118 -> 30 | R118: =F118+J118+N118 -> 50340 | S118: =G118+K118+O118 -> 52500 | T118: =S118-R101 -> 2160 | U118: =U117-R118+S118+V118-Custos!D118+Z117+AF117+AL117-AB117-AH117-AM117 -> 61829.415 | V118: =U117*(((1+Dashboard!$C$17)^(1/30))-1) -> 23.004237 | W118: =U118+R118 -> 112169.42 | X118: =-R118+S118-Custos!D118 -> 656.6 | Z118: 0 | AA118: =AC117*(((1+Dashboard!$C$20)^(1/30))-1) -> 289.48416 | AB118: 0 | AC118: =AC117+AA118-AB117+Z118 -> 631886.54 | AD118: =-Z118+AB118 -> 0 | AF118: 0 | AG118: =AI117*(((1+Dashboard!$C$21)^(1/30))-1) -> 54.19675 | AH118: 0 | AI118: =AI117+AG118-AH117+AF118 -> 105952.08 | AJ118: =-AF118+AH118 -> 0 | AL118: 0 | AM118: 0 | AN118: =-AL118+AM118 -> 0
... B378: =B377*(((1+Dashboard!$C$20)^(1/30))) -> 1186396.4 | C378: 374 | D378: =D377+1 -> 46547 | E378: =E377 -> 9 | F378: =E378*Dashboard!$I$3 -> 15102 | G378: =E361*Dashboard!$I$4 -> 15750 | I378: =I377 -> 9 | J378: =I378*Dashboard!$I$3 -> 15102 | K378: =I359*Dashboard!$I$4 -> 15750 | M378: =M377 -> 12 | N378: =M378*Dashboard!$I$3 -> 20136 | O378: =M357*Dashboard!$I$4 -> 21000 | Q378: =E378+I378+M378 -> 30 | R378: =F378+J378+N378 -> 50340 | S378: =G378+K378+O378 -> 52500 | T378: =S378-R361 -> 2160 | U378: =U377-R378+S378+V378-Custos!D378+Z377+AF377+AL377-AB377-AH377-AM377 -> 247489.89 | V378: =U377*(((1+Dashboard!$C$17)^(1/30))-1) -> 92.822464 | W378: =U378+R378 -> 297829.89 | X378: =-R378+S378-Custos!D378 -> 656.6 | Z378: 0 | AA378: =AC377*(((1+Dashboard!$C$20)^(1/30))-1) -> 326.11199 | AB378: 0 | AC378: =AC377+AA378-AB377+Z378 -> 711837.82 | AD378: =-Z378+AB378 -> 0 | AF378: 0 | AG378: =AI377*(((1+Dashboard!$C$21)^(1/30))-1) -> 61.908069 | AH378: 0 | AI378: =AI377+AG378-AH377+AF378 -> 121027.34 | AJ378: =-AF378+AH378 -> 0 | AL378: 0 | AM378: 0 | AN378: =-AL378+AM378 -> 0
B379: =B378*(((1+Dashboard!$C$20)^(1/30))) -> 1186940.1 | C379: 375 | D379: =D378+1 -> 46548 | E379: 0 | F379: =E379*Dashboard!$I$3 -> 0 | G379: =E362*Dashboard!$I$4 -> 15750 | I379: 0 | J379: =I379*Dashboard!$I$3 -> 0 | K379: =I360*Dashboard!$I$4 -> 15750 | M379: 0 | N379: =M379*Dashboard!$I$3 -> 0 | O379: =M358*Dashboard!$I$4 -> 21000 | Q379: =E379+I379+M379 -> 0 | R379: =F379+J379+N379 -> 0 | S379: =G379+K379+O379 -> 52500 | T379: =S379-R362 -> 2160 | U379: =U378-R379+S379+V379-Custos!D379+Z378+AF378+AL378-AB378-AH378-AM378 -> 298579.59 | V379: =U378*(((1+Dashboard!$C$17)^(1/30))-1) -> 93.104393 | W379: =U379+R379 -> 298579.59 | X379: =-R379+S379-Custos!D379 -> 50996.6 | Z379: 0 | AA379: =AC378*(((1+Dashboard!$C$20)^(1/30))-1) -> 326.26146 | AB379: 0 | AC379: =AC378+AA379-AB378+Z379 -> 712164.08 | AD379: =-Z379+AB379 -> 0 | AF379: 0 | AG379: =AI378*(((1+Dashboard!$C$21)^(1/30))-1) -> 61.939752 | AH379: 0 | AI379: =AI378+AG379-AH378+AF379 -> 121089.28 | AJ379: =-AF379+AH379 -> 0 | AL379: 0 | AM379: 0 | AN379: =-AL379+AM379 -> 0
B380: =B379*(((1+Dashboard!$C$20)^(1/30))) -> 1187484.2 | C380: 376 | D380: =D379+1 -> 46549 | E380: =E379 -> 0 | F380: =E380*Dashboard!$I$3 -> 0 | G380: =E363*Dashboard!$I$4 -> 15750 | I380: =I379 -> 0 | J380: =I380*Dashboard!$I$3 -> 0 | K380: =I361*Dashboard!$I$4 -> 15750 | M380: =M379 -> 0 | N380: =M380*Dashboard!$I$3 -> 0 | O380: =M359*Dashboard!$I$4 -> 21000 | Q380: =E380+I380+M380 -> 0 | R380: =F380+J380+N380 -> 0 | S380: =G380+K380+O380 -> 52500 | T380: =S380-R363 -> 2160 | U380: =U379-R380+S380+V380-Custos!D380+Z379+AF379+AL379-AB379-AH379-AM379 -> 350191.92 | V380: =U379*(((1+Dashboard!$C$17)^(1/30))-1) -> 112.32407 | W380: =U380+R380 -> 350191.92 | X380: =-R380+S380-Custos!D380 -> 51500 | Z380: 0 | AA380: =AC379*(((1+Dashboard!$C$20)^(1/30))-1) -> 326.41099 | AB380: 0 | AC380: =AC379+AA380-AB379+Z380 -> 712490.49 | AD380: =-Z380+AB380 -> 0 | AF380: 0 | AG380: =AI379*(((1+Dashboard!$C$21)^(1/30))-1) -> 61.971452 | AH380: 0 | AI380: =AI379+AG380-AH379+AF380 -> 121151.25 | AJ380: =-AF380+AH380 -> 0 | AL380: 0 | AM380: 0 | AN380: =-AL380+AM380 -> 0
B381: =B380*(((1+Dashboard!$C$20)^(1/30))) -> 1188028.4 | C381: 377 | D381: =D380+1 -> 46550 | E381: =E380 -> 0 | F381: =E381*Dashboard!$I$3 -> 0 | G381: =E364*Dashboard!$I$4 -> 15750 | I381: =I380 -> 0 | J381: =I381*Dashboard!$I$3 -> 0 | K381: =I362*Dashboard!$I$4 -> 15750 | M381: =M380 -> 0 | N381: =M381*Dashboard!$I$3 -> 0 | O381: =M360*Dashboard!$I$4 -> 21000 | Q381: =E381+I381+M381 -> 0 | R381: =F381+J381+N381 -> 0 | S381: =G381+K381+O381 -> 52500 | T381: =S381-R364 -> 2160 | U381: =U380-R381+S381+V381-Custos!D381+Z380+AF380+AL380-AB380-AH380-AM380 -> 401823.66 | V381: =U380*(((1+Dashboard!$C$17)^(1/30))-1) -> 131.74036 | W381: =U381+R381 -> 401823.66 | X381: =-R381+S381-Custos!D381 -> 51500 | Z381: 0 | AA381: =AC380*(((1+Dashboard!$C$20)^(1/30))-1) -> 326.5606 | AB381: 0 | AC381: =AC380+AA381-AB380+Z381 -> 712817.06 | AD381: =-Z381+AB381 -> 0 | AF381: 0 | AG381: =AI380*(((1+Dashboard!$C$21)^(1/30))-1) -> 62.003168 | AH381: 0 | AI381: =AI380+AG381-AH380+AF381 -> 121213.25 | AJ381: =-AF381+AH381 -> 0 | AL381: 0 | AM381: 0 | AN381: =-AL381+AM381 -> 0
B382: =B381*(((1+Dashboard!$C$20)^(1/30))) -> 1188572.9 | C382: 378 | D382: =D381+1 -> 46551 | E382: =E381 -> 0 | F382: =E382*Dashboard!$I$3 -> 0 | G382: =E365*Dashboard!$I$4 -> 15750 | I382: =I381 -> 0 | J382: =I382*Dashboard!$I$3 -> 0 | K382: =I363*Dashboard!$I$4 -> 15750 | M382: =M381 -> 0 | N382: =M382*Dashboard!$I$3 -> 0 | O382: =M361*Dashboard!$I$4 -> 21000 | Q382: =E382+I382+M382 -> 0 | R382: =F382+J382+N382 -> 0 | S382: =G382+K382+O382 -> 52500 | T382: =S382-R365 -> 2160 | U382: =U381-R382+S382+V382-Custos!D382+Z381+AF381+AL381-AB381-AH381-AM381 -> 453474.82 | V382: =U381*(((1+Dashboard!$C$17)^(1/30))-1) -> 151.16394 | W382: =U382+R382 -> 453474.82 | X382: =-R382+S382-Custos!D382 -> 51500 | Z382: 0 | AA382: =AC381*(((1+Dashboard!$C$20)^(1/30))-1) -> 326.71027 | AB382: 0 | AC382: =AC381+AA382-AB381+Z382 -> 713143.77 | AD382: =-Z382+AB382 -> 0 | AF382: 0 | AG382: =AI381*(((1+Dashboard!$C$21)^(1/30))-1) -> 62.0349 | AH382: 0 | AI382: =AI381+AG382-AH381+AF382 -> 121275.29 | AJ382: =-AF382+AH382 -> 0 | AL382: 0 | AM382: 0 | AN382: =-AL382+AM382 -> 0
B383: =B382*(((1+Dashboard!$C$20)^(1/30))) -> 1189117.7 | C383: 379 | D383: =D382+1 -> 46552 | E383: =E382 -> 0 | F383: =E383*Dashboard!$I$3 -> 0 | G383: =E366*Dashboard!$I$4 -> 15750 | I383: =I382 -> 0 | J383: =I383*Dashboard!$I$3 -> 0 | K383: =I364*Dashboard!$I$4 -> 15750 | M383: =M382 -> 0 | N383: =M383*Dashboard!$I$3 -> 0 | O383: =M362*Dashboard!$I$4 -> 21000 | Q383: =E383+I383+M383 -> 0 | R383: =F383+J383+N383 -> 0 | S383: =G383+K383+O383 -> 52500 | T383: =S383-R366 -> 2160 | U383: =U382-R383+S383+V383-Custos!D383+Z382+AF382+AL382-AB382-AH382-AM382 -> 505145.42 | V383: =U382*(((1+Dashboard!$C$17)^(1/30))-1) -> 170.59484 | W383: =U383+R383 -> 505145.42 | X383: =-R383+S383-Custos!D383 -> 51500 | Z383: 0 | AA383: =AC382*(((1+Dashboard!$C$20)^(1/30))-1) -> 326.86002 | AB383: 0 | AC383: =AC382+AA383-AB382+Z383 -> 713470.63 | AD383: =-Z383+AB383 -> 0 | AF383: 0 | AG383: =AI382*(((1+Dashboard!$C$21)^(1/30))-1) -> 62.066648 | AH383: 0 | AI383: =AI382+AG383-AH382+AF383 -> 121337.36 | AJ383: =-AF383+AH383 -> 0 | AL383: 0 | AM383: 0 | AN383: =-AL383+AM383 -> 0
B384: =B383*(((1+Dashboard!$C$20)^(1/30))) -> 1189662.7 | C384: 380 | D384: =D383+1 -> 46553 | E384: =E383 -> 0 | F384: =E384*Dashboard!$I$3 -> 0 | G384: =E367*Dashboard!$I$4 -> 15750 | I384: =I383 -> 0 | J384: =I384*Dashboard!$I$3 -> 0 | K384: =I365*Dashboard!$I$4 -> 15750 | M384: =M383 -> 0 | N384: =M384*Dashboard!$I$3 -> 0 | O384: =M363*Dashboard!$I$4 -> 21000 | Q384: =E384+I384+M384 -> 0 | R384: =F384+J384+N384 -> 0 | S384: =G384+K384+O384 -> 52500 | T384: =S384-R367 -> 2160 | U384: =U383-R384+S384+V384-Custos!D384+Z383+AF383+AL383-AB383-AH383-AM383 -> 556835.45 | V384: =U383*(((1+Dashboard!$C$17)^(1/30))-1) -> 190.03305 | W384: =U384+R384 -> 556835.45 | X384: =-R384+S384-Custos!D384 -> 51500 | Z384: 0 | AA384: =AC383*(((1+Dashboard!$C$20)^(1/30))-1) -> 327.00983 | AB384: 0 | AC384: =AC383+AA384-AB383+Z384 -> 713797.64 | AD384: =-Z384+AB384 -> 0 | AF384: 0 | AG384: =AI383*(((1+Dashboard!$C$21)^(1/30))-1) -> 62.098413 | AH384: 0 | AI384: =AI383+AG384-AH383+AF384 -> 121399.45 | AJ384: =-AF384+AH384 -> 0 | AL384: 0 | AM384: 0 | AN384: =-AL384+AM384 -> 0
B385: =B384*(((1+Dashboard!$C$20)^(1/30))) -> 1190208 | C385: 381 | D385: =D384+1 -> 46554 | E385: =E384 -> 0 | F385: =E385*Dashboard!$I$3 -> 0 | G385: =E368*Dashboard!$I$4 -> 15750 | I385: =I384 -> 0 | J385: =I385*Dashboard!$I$3 -> 0 | K385: =I366*Dashboard!$I$4 -> 15750 | M385: =M384 -> 0 | N385: =M385*Dashboard!$I$3 -> 0 | O385: =M364*Dashboard!$I$4 -> 21000 | Q385: =E385+I385+M385 -> 0 | R385: =F385+J385+N385 -> 0 | S385: =G385+K385+O385 -> 52500 | T385: =S385-R368 -> 2160 | U385: =U384-R385+S385+V385-Custos!D385+Z384+AF384+AL384-AB384-AH384-AM384 -> 608544.93 | V385: =U384*(((1+Dashboard!$C$17)^(1/30))-1) -> 209.47856 | W385: =U385+R385 -> 608544.93 | X385: =-R385+S385-Custos!D385 -> 51500 | Z385: 0 | AA385: =AC384*(((1+Dashboard!$C$20)^(1/30))-1) -> 327.15971 | AB385: 0 | AC385: =AC384+AA385-AB384+Z385 -> 714124.79 | AD385: =-Z385+AB385 -> 0 | AF385: 0 | AG385: =AI384*(((1+Dashboard!$C$21)^(1/30))-1) -> 62.130194 | AH385: 0 | AI385: =AI384+AG385-AH384+AF385 -> 121461.58 | AJ385: =-AF385+AH385 -> 0 | AL385: 0 | AM385: 0 | AN385: =-AL385+AM385 -> 0
B386: =B385*(((1+Dashboard!$C$20)^(1/30))) -> 1190753.5 | C386: 382 | D386: =D385+1 -> 46555 | E386: =E385 -> 0 | F386: =E386*Dashboard!$I$3 -> 0 | G386: =E369*Dashboard!$I$4 -> 15750 | I386: =I385 -> 0 | J386: =I386*Dashboard!$I$3 -> 0 | K386: =I367*Dashboard!$I$4 -> 15750 | M386: =M385 -> 0 | N386: =M386*Dashboard!$I$3 -> 0 | O386: =M365*Dashboard!$I$4 -> 21000 | Q386: =E386+I386+M386 -> 0 | R386: =F386+J386+N386 -> 0 | S386: =G386+K386+O386 -> 52500 | T386: =S386-R369 -> 2160 | U386: =U385-R386+S386+V386-Custos!D386+Z385+AF385+AL385-AB385-AH385-AM385 -> 660273.86 | V386: =U385*(((1+Dashboard!$C$17)^(1/30))-1) -> 228.9314 | W386: =U386+R386 -> 660273.86 | X386: =-R386+S386-Custos!D386 -> 51500 | Z386: 0 | AA386: =AC385*(((1+Dashboard!$C$20)^(1/30))-1) -> 327.30966 | AB386: 0 | AC386: =AC385+AA386-AB385+Z386 -> 714452.1 | AD386: =-Z386+AB386 -> 0 | AF386: 0 | AG386: =AI385*(((1+Dashboard!$C$21)^(1/30))-1) -> 62.161991 | AH386: 0 | AI386: =AI385+AG386-AH385+AF386 -> 121523.75 | AJ386: =-AF386+AH386 -> 0 | AL386: 0 | AM386: 0 | AN386: =-AL386+AM386 -> 0
B387: =B386*(((1+Dashboard!$C$20)^(1/30))) -> 1191299.3 | C387: 383 | D387: =D386+1 -> 46556 | E387: =E386 -> 0 | F387: =E387*Dashboard!$I$3 -> 0 | G387: =E370*Dashboard!$I$4 -> 15750 | I387: =I386 -> 0 | J387: =I387*Dashboard!$I$3 -> 0 | K387: =I368*Dashboard!$I$4 -> 15750 | M387: =M386 -> 0 | N387: =M387*Dashboard!$I$3 -> 0 | O387: =M366*Dashboard!$I$4 -> 21000 | Q387: =E387+I387+M387 -> 0 | R387: =F387+J387+N387 -> 0 | S387: =G387+K387+O387 -> 52500 | T387: =S387-R370 -> 2160 | U387: =U386-R387+S387+V387-Custos!D387+Z386+AF386+AL386-AB386-AH386-AM386 -> 712022.25 | V387: =U386*(((1+Dashboard!$C$17)^(1/30))-1) -> 248.39155 | W387: =U387+R387 -> 712022.25 | X387: =-R387+S387-Custos!D387 -> 51500 | Z387: 0 | AA387: =AC386*(((1+Dashboard!$C$20)^(1/30))-1) -> 327.45968 | AB387: 0 | AC387: =AC386+AA387-AB386+Z387 -> 714779.56 | AD387: =-Z387+AB387 -> 0 | AF387: 0 | AG387: =AI386*(((1+Dashboard!$C$21)^(1/30))-1) -> 62.193805 | AH387: 0 | AI387: =AI386+AG387-AH386+AF387 -> 121585.94 | AJ387: =-AF387+AH387 -> 0 | AL387: 0 | AM387: 0 | AN387: =-AL387+AM387 -> 0
B388: =B387*(((1+Dashboard!$C$20)^(1/30))) -> 1191845.3 | C388: 384 | D388: =D387+1 -> 46557 | E388: =E387 -> 0 | F388: =E388*Dashboard!$I$3 -> 0 | G388: =E371*Dashboard!$I$4 -> 15750 | I388: =I387 -> 0 | J388: =I388*Dashboard!$I$3 -> 0 | K388: =I369*Dashboard!$I$4 -> 15750 | M388: =M387 -> 0 | N388: =M388*Dashboard!$I$3 -> 0 | O388: =M367*Dashboard!$I$4 -> 21000 | Q388: =E388+I388+M388 -> 0 | R388: =F388+J388+N388 -> 0 | S388: =G388+K388+O388 -> 52500 | T388: =S388-R371 -> 2160 | U388: =U387-R388+S388+V388-Custos!D388+Z387+AF387+AL387-AB387-AH387-AM387 -> 763790.11 | V388: =U387*(((1+Dashboard!$C$17)^(1/30))-1) -> 267.85902 | W388: =U388+R388 -> 763790.11 | X388: =-R388+S388-Custos!D388 -> 51500 | Z388: 0 | AA388: =AC387*(((1+Dashboard!$C$20)^(1/30))-1) -> 327.60976 | AB388: 0 | AC388: =AC387+AA388-AB387+Z388 -> 715107.17 | AD388: =-Z388+AB388 -> 0 | AF388: 0 | AG388: =AI387*(((1+Dashboard!$C$21)^(1/30))-1) -> 62.225634 | AH388: 0 | AI388: =AI387+AG388-AH387+AF388 -> 121648.17 | AJ388: =-AF388+AH388 -> 0 | AL388: 0 | AM388: 0 | AN388: =-AL388+AM388 -> 0
B389: =B388*(((1+Dashboard!$C$20)^(1/30))) -> 1192391.6 | C389: 385 | D389: =D388+1 -> 46558 | E389: =E388 -> 0 | F389: =E389*Dashboard!$I$3 -> 0 | G389: =E372*Dashboard!$I$4 -> 15750 | I389: =I388 -> 0 | J389: =I389*Dashboard!$I$3 -> 0 | K389: =I370*Dashboard!$I$4 -> 15750 | M389: =M388 -> 0 | N389: =M389*Dashboard!$I$3 -> 0 | O389: =M368*Dashboard!$I$4 -> 21000 | Q389: =E389+I389+M389 -> 0 | R389: =F389+J389+N389 -> 0 | S389: =G389+K389+O389 -> 52500 | T389: =S389-R372 -> 2160 | U389: =U388-R389+S389+V389-Custos!D389+Z388+AF388+AL388-AB388-AH388-AM388 -> 815577.44 | V389: =U388*(((1+Dashboard!$C$17)^(1/30))-1) -> 287.33382 | W389: =U389+R389 -> 815577.44 | X389: =-R389+S389-Custos!D389 -> 51500 | Z389: 0 | AA389: =AC388*(((1+Dashboard!$C$20)^(1/30))-1) -> 327.75992 | AB389: 0 | AC389: =AC388+AA389-AB388+Z389 -> 715434.93 | AD389: =-Z389+AB389 -> 0 | AF389: 0 | AG389: =AI388*(((1+Dashboard!$C$21)^(1/30))-1) -> 62.25748 | AH389: 0 | AI389: =AI388+AG389-AH388+AF389 -> 121710.42 | AJ389: =-AF389+AH389 -> 0 | AL389: 0 | AM389: 0 | AN389: =-AL389+AM389 -> 0
B390: =B389*(((1+Dashboard!$C$20)^(1/30))) -> 1192938.1 | C390: 386 | D390: =D389+1 -> 46559 | E390: =E389 -> 0 | F390: =E390*Dashboard!$I$3 -> 0 | G390: =E373*Dashboard!$I$4 -> 15750 | I390: =I389 -> 0 | J390: =I390*Dashboard!$I$3 -> 0 | K390: =I371*Dashboard!$I$4 -> 15750 | M390: =M389 -> 0 | N390: =M390*Dashboard!$I$3 -> 0 | O390: =M369*Dashboard!$I$4 -> 21000 | Q390: =E390+I390+M390 -> 0 | R390: =F390+J390+N390 -> 0 | S390: =G390+K390+O390 -> 52500 | T390: =S390-R373 -> 2160 | U390: =U389-R390+S390+V390-Custos!D390+Z389+AF389+AL389-AB389-AH389-AM389 -> 867384.26 | V390: =U389*(((1+Dashboard!$C$17)^(1/30))-1) -> 306.81594 | W390: =U390+R390 -> 867384.26 | X390: =-R390+S390-Custos!D390 -> 51500 | Z390: 0 | AA390: =AC389*(((1+Dashboard!$C$20)^(1/30))-1) -> 327.91014 | AB390: 0 | AC390: =AC389+AA390-AB389+Z390 -> 715762.84 | AD390: =-Z390+AB390 -> 0 | AF390: 0 | AG390: =AI389*(((1+Dashboard!$C$21)^(1/30))-1) -> 62.289343 | AH390: 0 | AI390: =AI389+AG390-AH389+AF390 -> 121772.71 | AJ390: =-AF390+AH390 -> 0 | AL390: 0 | AM390: 0 | AN390: =-AL390+AM390 -> 0
B391: =B390*(((1+Dashboard!$C$20)^(1/30))) -> 1193484.8 | C391: 387 | D391: =D390+1 -> 46560 | E391: =E390 -> 0 | F391: =E391*Dashboard!$I$3 -> 0 | G391: =E374*Dashboard!$I$4 -> 15750 | I391: =I390 -> 0 | J391: =I391*Dashboard!$I$3 -> 0 | K391: =I372*Dashboard!$I$4 -> 15750 | M391: =M390 -> 0 | N391: =M391*Dashboard!$I$3 -> 0 | O391: =M370*Dashboard!$I$4 -> 21000 | Q391: =E391+I391+M391 -> 0 | R391: =F391+J391+N391 -> 0 | S391: =G391+K391+O391 -> 52500 | T391: =S391-R374 -> 2160 | U391: =U390-R391+S391+V391-Custos!D391+Z390+AF390+AL390-AB390-AH390-AM390 -> 919210.56 | V391: =U390*(((1+Dashboard!$C$17)^(1/30))-1) -> 326.30539 | W391: =U391+R391 -> 919210.56 | X391: =-R391+S391-Custos!D391 -> 51500 | Z391: 0 | AA391: =AC390*(((1+Dashboard!$C$20)^(1/30))-1) -> 328.06044 | AB391: 0 | AC391: =AC390+AA391-AB390+Z391 -> 716090.9 | AD391: =-Z391+AB391 -> 0 | AF391: 0 | AG391: =AI390*(((1+Dashboard!$C$21)^(1/30))-1) -> 62.321221 | AH391: 0 | AI391: =AI390+AG391-AH390+AF391 -> 121835.03 | AJ391: =-AF391+AH391 -> 0 | AL391: 0 | AM391: 0 | AN391: =-AL391+AM391 -> 0
... B398: =B397*(((1+Dashboard!$C$20)^(1/30))) -> 1197319.2 | C398: 394 | D398: =D397+1 -> 46567 | E398: =E397 -> 0 | F398: =E398*Dashboard!$I$3 -> 0 | G398: =E381*Dashboard!$I$4 -> 0 | I398: =I397 -> 0 | J398: =I398*Dashboard!$I$3 -> 0 | K398: =I379*Dashboard!$I$4 -> 0 | M398: =M397 -> 0 | N398: =M398*Dashboard!$I$3 -> 0 | O398: =M377*Dashboard!$I$4 -> 21000 | Q398: =E398+I398+M398 -> 0 | R398: =F398+J398+N398 -> 0 | S398: =G398+K398+O398 -> 21000 | T398: =S398-R381 -> 21000 | U398: =U397-R398+S398+V398-Custos!D398+Z397+AF397+AL397-AB397-AH397-AM397 -> 1219523.2 | V398: =U397*(((1+Dashboard!$C$17)^(1/30))-1) -> 451.08463 | W398: =U398+R398 -> 1219523.2 | X398: =-R398+S398-Custos!D398 -> 20000 | Z398: 0 | AA398: =AC397*(((1+Dashboard!$C$20)^(1/30))-1) -> 329.11442 | AB398: 0 | AC398: =AC397+AA398-AB397+Z398 -> 718391.54 | AD398: =-Z398+AB398 -> 0 | AF398: 0 | AG398: =AI397*(((1+Dashboard!$C$21)^(1/30))-1) -> 62.544829 | AH398: 0 | AI398: =AI397+AG398-AH397+AF398 -> 122272.18 | AJ398: =-AF398+AH398 -> 0 | AL398: 0 | AM398: 0 | AN398: =-AL398+AM398 -> 0
B399: =B398*(((1+Dashboard!$C$20)^(1/30))) -> 1197868 | C399: 395 | D399: =D398+1 -> 46568 | E399: =E398 -> 0 | F399: =E399*Dashboard!$I$3 -> 0 | G399: =E382*Dashboard!$I$4 -> 0 | I399: =I398 -> 0 | J399: =I399*Dashboard!$I$3 -> 0 | K399: =I380*Dashboard!$I$4 -> 0 | M399: =M398 -> 0 | N399: =M399*Dashboard!$I$3 -> 0 | O399: =M378*Dashboard!$I$4 -> 21000 | Q399: =E399+I399+M399 -> 0 | R399: =F399+J399+N399 -> 0 | S399: =G399+K399+O399 -> 21000 | T399: =S399-R382 -> 21000 | U399: =U398-R399+S399+V399-Custos!D399+Z398+AF398+AL398-AB398-AH398-AM398 -> 1239982 | V399: =U398*(((1+Dashboard!$C$17)^(1/30))-1) -> 458.77822 | W399: =U399+R399 -> 1239982 | X399: =-R399+S399-Custos!D399 -> 20000 | Z399: 0 | AA399: =AC398*(((1+Dashboard!$C$20)^(1/30))-1) -> 329.26527 | AB399: =AC399 -> 718720.81 | AC399: =AC398+AA399-AB398+Z399 -> 718720.81 | AD399: =-Z399+AB399 -> 718720.81 | AF399: 0 | AG399: =AI398*(((1+Dashboard!$C$21)^(1/30))-1) -> 62.576838 | AH399: =AI399 -> 122334.75 | AI399: =AI398+AG399-AH398+AF399 -> 122334.75 | AJ399: =-AF399+AH399 -> 122334.75 | AL399: 0 | AM399: =U399-AB399-AH399 -> 398926.46 | AN399: =-AL399+AM399 -> 398926.46

Sheet Custos
D2: Custos
B3: m | C3: Data | D3: TOTAL | E3: Custo Adm | F3: Custo Gestão | G3: Consultoria | H3: Performance | I3: Outros
B4: 0
B5: 1 | C5: 46174 | D5: =E5+F5+G5+H5+I5 -> 11000 | E5: =Dashboard!$J$16/30 -> 500 | F5: =Dashboard!$J$15/30 -> 500 | G5: 0 | H5: 0 | I5: 10000
B6: 2 | C6: =C5+1 -> 46175 | D6: =E6+F6+G6+H6+I6 -> 1503.4 | E6: =MAX(Dashboard!$J$16,(Dashboard!$I$16*Fundo!W5)/360)/30 -> 500 | F6: =MAX(Dashboard!$J$15,(Dashboard!$I$15*Fundo!W5)/360)/30 -> 500 | G6: =Fundo!R5*Dashboard!$I$14 -> 503.4 | H6: 0
B7: 3 | C7: =C6+1 -> 46176 | D7: =E7+F7+G7+H7+I7 -> 1503.4 | E7: =MAX(Dashboard!$J$16,(Dashboard!$I$16*Fundo!W6)/360)/30 -> 500 | F7: =MAX(Dashboard!$J$15,(Dashboard!$I$15*Fundo!W6)/360)/30 -> 500 | G7: =Fundo!R6*Dashboard!$I$14 -> 503.4 | H7: 0
B8: 4 | C8: =C7+1 -> 46177 | D8: =E8+F8+G8+H8+I8 -> 1503.4 | E8: =MAX(Dashboard!$J$16,(Dashboard!$I$16*Fundo!W7)/360)/30 -> 500 | F8: =MAX(Dashboard!$J$15,(Dashboard!$I$15*Fundo!W7)/360)/30 -> 500 | G8: =Fundo!R7*Dashboard!$I$14 -> 503.4 | H8: 0
B9: 5 | C9: =C8+1 -> 46178 | D9: =E9+F9+G9+H9+I9 -> 1503.4 | E9: =MAX(Dashboard!$J$16,(Dashboard!$I$16*Fundo!W8)/360)/30 -> 500 | F9: =MAX(Dashboard!$J$15,(Dashboard!$I$15*Fundo!W8)/360)/30 -> 500 | G9: =Fundo!R8*Dashboard!$I$14 -> 503.4 | H9: 0
B10: 6 | C10: =C9+1 -> 46179 | D10: =E10+F10+G10+H10+I10 -> 1503.4 | E10: =MAX(Dashboard!$J$16,(Dashboard!$I$16*Fundo!W9)/360)/30 -> 500 | F10: =MAX(Dashboard!$J$15,(Dashboard!$I$15*Fundo!W9)/360)/30 -> 500 | G10: =Fundo!R9*Dashboard!$I$14 -> 503.4 | H10: 0
B11: 7 | C11: =C10+1 -> 46180 | D11: =E11+F11+G11+H11+I11 -> 1503.4 | E11: =MAX(Dashboard!$J$16,(Dashboard!$I$16*Fundo!W10)/360)/30 -> 500 | F11: =MAX(Dashboard!$J$15,(Dashboard!$I$15*Fundo!W10)/360)/30 -> 500 | G11: =Fundo!R10*Dashboard!$I$14 -> 503.4 | H11: 0
B12: 8 | C12: =C11+1 -> 46181 | D12: =E12+F12+G12+H12+I12 -> 1503.4 | E12: =MAX(Dashboard!$J$16,(Dashboard!$I$16*Fundo!W11)/360)/30 -> 500 | F12: =MAX(Dashboard!$J$15,(Dashboard!$I$15*Fundo!W11)/360)/30 -> 500 | G12: =Fundo!R11*Dashboard!$I$14 -> 503.4 | H12: 0
B13: 9 | C13: =C12+1 -> 46182 | D13: =E13+F13+G13+H13+I13 -> 1503.4 | E13: =MAX(Dashboard!$J$16,(Dashboard!$I$16*Fundo!W12)/360)/30 -> 500 | F13: =MAX(Dashboard!$J$15,(Dashboard!$I$15*Fundo!W12)/360)/30 -> 500 | G13: =Fundo!R12*Dashboard!$I$14 -> 503.4 | H13: 0
B14: 10 | C14: =C13+1 -> 46183 | D14: =E14+F14+G14+H14+I14 -> 1503.4 | E14: =MAX(Dashboard!$J$16,(Dashboard!$I$16*Fundo!W13)/360)/30 -> 500 | F14: =MAX(Dashboard!$J$15,(Dashboard!$I$15*Fundo!W13)/360)/30 -> 500 | G14: =Fundo!R13*Dashboard!$I$14 -> 503.4 | H14: 0
B15: 11 | C15: =C14+1 -> 46184 | D15: =E15+F15+G15+H15+I15 -> 1503.4 | E15: =MAX(Dashboard!$J$16,(Dashboard!$I$16*Fundo!W14)/360)/30 -> 500 | F15: =MAX(Dashboard!$J$15,(Dashboard!$I$15*Fundo!W14)/360)/30 -> 500 | G15: =Fundo!R14*Dashboard!$I$14 -> 503.4 | H15: 0
B16: 12 | C16: =C15+1 -> 46185 | D16: =E16+F16+G16+H16+I16 -> 1503.4 | E16: =MAX(Dashboard!$J$16,(Dashboard!$I$16*Fundo!W15)/360)/30 -> 500 | F16: =MAX(Dashboard!$J$15,(Dashboard!$I$15*Fundo!W15)/360)/30 -> 500 | G16: =Fundo!R15*Dashboard!$I$14 -> 503.4 | H16: 0
B17: 13 | C17: =C16+1 -> 46186 | D17: =E17+F17+G17+H17+I17 -> 1503.4 | E17: =MAX(Dashboard!$J$16,(Dashboard!$I$16*Fundo!W16)/360)/30 -> 500 | F17: =MAX(Dashboard!$J$15,(Dashboard!$I$15*Fundo!W16)/360)/30 -> 500 | G17: =Fundo!R16*Dashboard!$I$14 -> 503.4 | H17: 0
... B403: 399 | C403: =C402+1 -> 46572 | D403: =E403+F403+G403+H403+I403 -> 1000 | E403: =MAX(Dashboard!$J$16,(Dashboard!$I$16*Fundo!W402)/360)/30 -> 500 | F403: =MAX(Dashboard!$J$15,(Dashboard!$I$15*Fundo!W402)/360)/30 -> 500 | G403: =Fundo!R402*Dashboard!$I$14 -> 0 | H403: 0
